{"EventName":"StartSession","TimestampUTC":1756823234.170000,"RecordId":0,"ProjectName":"WarehouseWreckage","ProjectID":"00000000000000000000000000000000","Session_ID":"{1CA7FCE3-412D-5A25-3428-5294C53E8240}","Session_Label":"","Session_StartUTC":1756823234.17,"Build_Configuration":"Development","Build_IsInternalBuild":false,"Build_IsPerforceBuild":false,"Build_IsPromotedBuild":true,"Build_BranchName":"++ue5+release-5.4","Build_Changelist":35576357,"Hardware_Platform":"Windows","Hardware_GPU":"","Hardware_CPU":"AMD Ryzen 5 9600X 6-Core Processor             ","Hardware_CPU_Cores_Physical":6,"Hardware_CPU_Cores_Logical":12,"Hardware_RAM":66182578176,"Hardware_ComputerName":"MVAT4","Config_IsEditor":true,"Config_IsUnattended":false,"Config_IsBuildMachine":false,"Config_IsRunningCommandlet":false,"Config_IsDebuggerPresent":false}
{"EventName":"Editor.AssetRegistry.Startup","TimestampUTC":1756823236.514000,"RecordId":1,"ProjectName":"WarehouseWreckage","ProjectID":"00000000000000000000000000000000","Session_ID":"{1CA7FCE3-412D-5A25-3428-5294C53E8240}","Session_Label":"","Session_StartUTC":1756823234.17,"Build_Configuration":"Development","Build_IsInternalBuild":false,"Build_IsPerforceBuild":false,"Build_IsPromotedBuild":true,"Build_BranchName":"++ue5+release-5.4","Build_Changelist":35576357,"Hardware_Platform":"Windows","Hardware_GPU":"","Hardware_CPU":"AMD Ryzen 5 9600X 6-Core Processor             ","Hardware_CPU_Cores_Physical":6,"Hardware_CPU_Cores_Logical":12,"Hardware_RAM":66182578176,"Hardware_ComputerName":"MVAT4","Config_IsEditor":true,"Config_IsUnattended":false,"Config_IsBuildMachine":false,"Config_IsRunningCommandlet":false,"Config_IsDebuggerPresent":false,"SchemaVersion":1,"Duration":0.001599,"StartedAsyncGather":true}
{"EventName":"Span","TimestampUTC":1756823239.517000,"RecordId":2,"ProjectName":"WarehouseWreckage","ProjectID":"00000000000000000000000000000000","Session_ID":"{1CA7FCE3-412D-5A25-3428-5294C53E8240}","Session_Label":"","Session_StartUTC":1756823234.17,"Build_Configuration":"Development","Build_IsInternalBuild":false,"Build_IsPerforceBuild":false,"Build_IsPromotedBuild":true,"Build_BranchName":"++ue5+release-5.4","Build_Changelist":35576357,"Hardware_Platform":"Windows","Hardware_GPU":"","Hardware_CPU":"AMD Ryzen 5 9600X 6-Core Processor             ","Hardware_CPU_Cores_Physical":6,"Hardware_CPU_Cores_Logical":12,"Hardware_RAM":66182578176,"Hardware_ComputerName":"MVAT4","Config_IsEditor":true,"Config_IsUnattended":false,"Config_IsBuildMachine":false,"Config_IsRunningCommandlet":false,"Config_IsDebuggerPresent":false,"MapName":"None","SchemaVersion":1,"Span_Name":"Editor.Boot","Span_GUID":"30F8CF3F433CB195CC599BA104181DD2","Span_ParentName":"Editor","Span_ThreadId":30336,"Span_Depth":2,"Span_StartUTC":1756823234.173,"Span_EndUTC":1756823239.517,"Span_TimeInSec":5.344}
{"EventName":"Core.Loading","TimestampUTC":1756823239.519000,"RecordId":3,"ProjectName":"WarehouseWreckage","ProjectID":"00000000000000000000000000000000","Session_ID":"{1CA7FCE3-412D-5A25-3428-5294C53E8240}","Session_Label":"","Session_StartUTC":1756823234.17,"Build_Configuration":"Development","Build_IsInternalBuild":false,"Build_IsPerforceBuild":false,"Build_IsPromotedBuild":true,"Build_BranchName":"++ue5+release-5.4","Build_Changelist":35576357,"Hardware_Platform":"Windows","Hardware_GPU":"","Hardware_CPU":"AMD Ryzen 5 9600X 6-Core Processor             ","Hardware_CPU_Cores_Physical":6,"Hardware_CPU_Cores_Logical":12,"Hardware_RAM":66182578176,"Hardware_ComputerName":"MVAT4","Config_IsEditor":true,"Config_IsUnattended":false,"Config_IsBuildMachine":false,"Config_IsRunningCommandlet":false,"Config_IsDebuggerPresent":false,"MapName":"None","SchemaVersion":3,"LoadingName":"BootEditor","LoadingSeconds":5.344,"DDC_Summary_BackEnd":"InstalledDerivedDataBackendGraph","DDC_Summary_HasLocalCache":"true","DDC_Summary_HasSharedCache":"false","DDC_Summary_HasCloudCache":"false","DDC_Summary_HasZenCache":"true","DDC_Summary_TotalGetHits":892.0,"DDC_Summary_TotalGetMisses":92.0,"DDC_Summary_TotalGets":984.0,"DDC_Summary_TotalGetHitPct":0.906504,"DDC_Summary_GetMissPct":0.093496,"DDC_Summary_TotalPutHits":86.0,"DDC_Summary_TotalPutMisses":0.0,"DDC_Summary_TotalPuts":86.0,"DDC_Summary_TotalPutHitPct":1.0,"DDC_Summary_PutMissPct":0.0,"DDC_Summary_LocalGetHits":0.0,"DDC_Summary_LocalGetTotal":0.0,"DDC_Summary_LocalGetHitPct":0.0,"DDC_Summary_SharedGetHits":0.0,"DDC_Summary_SharedGetTotal":0.0,"DDC_Summary_SharedGetHitPct":0.0,"DDC_Summary_ZenLocalGetHits":579.0,"DDC_Summary_ZenLocalGetTotal":671.0,"DDC_Summary_ZenLocalGetHitPct":0.862891,"DDC_Summary_ZenRemoteGetHits":0.0,"DDC_Summary_ZenRemoteGetTotal":0.0,"DDC_Summary_ZenRemoteGetHitPct":0.0,"DDC_Summary_CloudGetHits":0.0,"DDC_Summary_CloudGetTotal":0.0,"DDC_Summary_CloudGetHitPct":0.0,"DDC_Summary_LocalLatency":0.0,"DDC_Summary_LocalReadSpeed":0.0,"DDC_Summary_LocalWriteSpeed":0.0,"DDC_Summary_SharedLatency":0.0,"DDC_Summary_SharedReadSpeed":0.0,"DDC_Summary_SharedWriteSpeed":0.0,"DDC_Summary_CloudLatency":0.0,"DDC_Summary_CloudReadSpeed":0.0,"DDC_Summary_CloudWriteSpeed":0.0}
{"EventName":"Core.DDC.Resource","TimestampUTC":1756823239.520000,"RecordId":4,"ProjectName":"WarehouseWreckage","ProjectID":"00000000000000000000000000000000","Session_ID":"{1CA7FCE3-412D-5A25-3428-5294C53E8240}","Session_Label":"","Session_StartUTC":1756823234.17,"Build_Configuration":"Development","Build_IsInternalBuild":false,"Build_IsPerforceBuild":false,"Build_IsPromotedBuild":true,"Build_BranchName":"++ue5+release-5.4","Build_Changelist":35576357,"Hardware_Platform":"Windows","Hardware_GPU":"","Hardware_CPU":"AMD Ryzen 5 9600X 6-Core Processor             ","Hardware_CPU_Cores_Physical":6,"Hardware_CPU_Cores_Logical":12,"Hardware_RAM":66182578176,"Hardware_ComputerName":"MVAT4","Config_IsEditor":true,"Config_IsUnattended":false,"Config_IsBuildMachine":false,"Config_IsRunningCommandlet":false,"Config_IsDebuggerPresent":false,"MapName":"None","SchemaVersion":3,"LoadingName":"BootEditor","AssetType":"Texture (Inline)","Load_Count":98,"Load_TimeSec":0.011355,"Load_SizeMB":52.432806,"Build_Count":0,"Build_TimeSec":0.0,"Build_SizeMB":0.0,"Total_Count":98,"Total_TimeSec":0.011355,"Total_SizeMB":52,"Efficiency":1.0,"Thread_TimeSec":0.011355}
{"EventName":"Core.DDC.Resource","TimestampUTC":1756823239.521000,"RecordId":5,"ProjectName":"WarehouseWreckage","ProjectID":"00000000000000000000000000000000","Session_ID":"{1CA7FCE3-412D-5A25-3428-5294C53E8240}","Session_Label":"","Session_StartUTC":1756823234.17,"Build_Configuration":"Development","Build_IsInternalBuild":false,"Build_IsPerforceBuild":false,"Build_IsPromotedBuild":true,"Build_BranchName":"++ue5+release-5.4","Build_Changelist":35576357,"Hardware_Platform":"Windows","Hardware_GPU":"","Hardware_CPU":"AMD Ryzen 5 9600X 6-Core Processor             ","Hardware_CPU_Cores_Physical":6,"Hardware_CPU_Cores_Logical":12,"Hardware_RAM":66182578176,"Hardware_ComputerName":"MVAT4","Config_IsEditor":true,"Config_IsUnattended":false,"Config_IsBuildMachine":false,"Config_IsRunningCommandlet":false,"Config_IsDebuggerPresent":false,"MapName":"None","SchemaVersion":3,"LoadingName":"BootEditor","AssetType":"Texture (Streaming)","Load_Count":30,"Load_TimeSec":0.003417,"Load_SizeMB":8.521484,"Build_Count":0,"Build_TimeSec":0.0,"Build_SizeMB":0.0,"Total_Count":30,"Total_TimeSec":0.003417,"Total_SizeMB":8,"Efficiency":1.0,"Thread_TimeSec":0.003417}
{"EventName":"Core.DDC.Resource","TimestampUTC":1756823239.522000,"RecordId":6,"ProjectName":"WarehouseWreckage","ProjectID":"00000000000000000000000000000000","Session_ID":"{1CA7FCE3-412D-5A25-3428-5294C53E8240}","Session_Label":"","Session_StartUTC":1756823234.17,"Build_Configuration":"Development","Build_IsInternalBuild":false,"Build_IsPerforceBuild":false,"Build_IsPromotedBuild":true,"Build_BranchName":"++ue5+release-5.4","Build_Changelist":35576357,"Hardware_Platform":"Windows","Hardware_GPU":"","Hardware_CPU":"AMD Ryzen 5 9600X 6-Core Processor             ","Hardware_CPU_Cores_Physical":6,"Hardware_CPU_Cores_Logical":12,"Hardware_RAM":66182578176,"Hardware_ComputerName":"MVAT4","Config_IsEditor":true,"Config_IsUnattended":false,"Config_IsBuildMachine":false,"Config_IsRunningCommandlet":false,"Config_IsDebuggerPresent":false,"MapName":"None","SchemaVersion":3,"LoadingName":"BootEditor","AssetType":"StaticMesh","Load_Count":35,"Load_TimeSec":0.007629,"Load_SizeMB":4.230455,"Build_Count":0,"Build_TimeSec":0.0,"Build_SizeMB":0.0,"Total_Count":35,"Total_TimeSec":0.007629,"Total_SizeMB":4,"Efficiency":1.0,"Thread_TimeSec":0.006869}
{"EventName":"Core.DDC.Resource","TimestampUTC":1756823239.523000,"RecordId":7,"ProjectName":"WarehouseWreckage","ProjectID":"00000000000000000000000000000000","Session_ID":"{1CA7FCE3-412D-5A25-3428-5294C53E8240}","Session_Label":"","Session_StartUTC":1756823234.17,"Build_Configuration":"Development","Build_IsInternalBuild":false,"Build_IsPerforceBuild":false,"Build_IsPromotedBuild":true,"Build_BranchName":"++ue5+release-5.4","Build_Changelist":35576357,"Hardware_Platform":"Windows","Hardware_GPU":"","Hardware_CPU":"AMD Ryzen 5 9600X 6-Core Processor             ","Hardware_CPU_Cores_Physical":6,"Hardware_CPU_Cores_Logical":12,"Hardware_RAM":66182578176,"Hardware_ComputerName":"MVAT4","Config_IsEditor":true,"Config_IsUnattended":false,"Config_IsBuildMachine":false,"Config_IsRunningCommandlet":false,"Config_IsDebuggerPresent":false,"MapName":"None","SchemaVersion":3,"LoadingName":"BootEditor","AssetType":"GlobalShader","Load_Count":346,"Load_TimeSec":0.03925,"Load_SizeMB":106.153169,"Build_Count":0,"Build_TimeSec":0.0,"Build_SizeMB":0.0,"Total_Count":346,"Total_TimeSec":0.03925,"Total_SizeMB":106,"Efficiency":1.0,"Thread_TimeSec":0.03925}
{"EventName":"Core.DDC.Resource","TimestampUTC":1756823239.524000,"RecordId":8,"ProjectName":"WarehouseWreckage","ProjectID":"00000000000000000000000000000000","Session_ID":"{1CA7FCE3-412D-5A25-3428-5294C53E8240}","Session_Label":"","Session_StartUTC":1756823234.17,"Build_Configuration":"Development","Build_IsInternalBuild":false,"Build_IsPerforceBuild":false,"Build_IsPromotedBuild":true,"Build_BranchName":"++ue5+release-5.4","Build_Changelist":35576357,"Hardware_Platform":"Windows","Hardware_GPU":"","Hardware_CPU":"AMD Ryzen 5 9600X 6-Core Processor             ","Hardware_CPU_Cores_Physical":6,"Hardware_CPU_Cores_Logical":12,"Hardware_RAM":66182578176,"Hardware_ComputerName":"MVAT4","Config_IsEditor":true,"Config_IsUnattended":false,"Config_IsBuildMachine":false,"Config_IsRunningCommandlet":false,"Config_IsDebuggerPresent":false,"MapName":"None","SchemaVersion":3,"LoadingName":"BootEditor","AssetType":"BodySetup","Load_Count":1,"Load_TimeSec":0.001331,"Load_SizeMB":1.456863,"Build_Count":0,"Build_TimeSec":0.0,"Build_SizeMB":0.0,"Total_Count":1,"Total_TimeSec":0.001331,"Total_SizeMB":1,"Efficiency":1.0,"Thread_TimeSec":0.001331}
{"EventName":"Core.DDC.Resource","TimestampUTC":1756823239.525000,"RecordId":9,"ProjectName":"WarehouseWreckage","ProjectID":"00000000000000000000000000000000","Session_ID":"{1CA7FCE3-412D-5A25-3428-5294C53E8240}","Session_Label":"","Session_StartUTC":1756823234.17,"Build_Configuration":"Development","Build_IsInternalBuild":false,"Build_IsPerforceBuild":false,"Build_IsPromotedBuild":true,"Build_BranchName":"++ue5+release-5.4","Build_Changelist":35576357,"Hardware_Platform":"Windows","Hardware_GPU":"","Hardware_CPU":"AMD Ryzen 5 9600X 6-Core Processor             ","Hardware_CPU_Cores_Physical":6,"Hardware_CPU_Cores_Logical":12,"Hardware_RAM":66182578176,"Hardware_ComputerName":"MVAT4","Config_IsEditor":true,"Config_IsUnattended":false,"Config_IsBuildMachine":false,"Config_IsRunningCommandlet":false,"Config_IsDebuggerPresent":false,"MapName":"None","SchemaVersion":3,"LoadingName":"BootEditor","AssetType":"CardRepresentation","Load_Count":35,"Load_TimeSec":0.002049,"Load_SizeMB":0.009989,"Build_Count":0,"Build_TimeSec":0.0,"Build_SizeMB":0.0,"Total_Count":35,"Total_TimeSec":0.002049,"Total_SizeMB":0,"Efficiency":1.0,"Thread_TimeSec":0.001906}
{"EventName":"Core.DDC.Resource","TimestampUTC":1756823239.525000,"RecordId":10,"ProjectName":"WarehouseWreckage","ProjectID":"00000000000000000000000000000000","Session_ID":"{1CA7FCE3-412D-5A25-3428-5294C53E8240}","Session_Label":"","Session_StartUTC":1756823234.17,"Build_Configuration":"Development","Build_IsInternalBuild":false,"Build_IsPerforceBuild":false,"Build_IsPromotedBuild":true,"Build_BranchName":"++ue5+release-5.4","Build_Changelist":35576357,"Hardware_Platform":"Windows","Hardware_GPU":"","Hardware_CPU":"AMD Ryzen 5 9600X 6-Core Processor             ","Hardware_CPU_Cores_Physical":6,"Hardware_CPU_Cores_Logical":12,"Hardware_RAM":66182578176,"Hardware_ComputerName":"MVAT4","Config_IsEditor":true,"Config_IsUnattended":false,"Config_IsBuildMachine":false,"Config_IsRunningCommandlet":false,"Config_IsDebuggerPresent":false,"MapName":"None","SchemaVersion":3,"LoadingName":"BootEditor","AssetType":"MaterialShader","Load_Count":4,"Load_TimeSec":0.00698,"Load_SizeMB":17.932115,"Build_Count":0,"Build_TimeSec":0.0,"Build_SizeMB":0.0,"Total_Count":4,"Total_TimeSec":0.00698,"Total_SizeMB":17,"Efficiency":1.0,"Thread_TimeSec":0.00698}
{"EventName":"Core.DDC.Resource","TimestampUTC":1756823239.526000,"RecordId":11,"ProjectName":"WarehouseWreckage","ProjectID":"00000000000000000000000000000000","Session_ID":"{1CA7FCE3-412D-5A25-3428-5294C53E8240}","Session_Label":"","Session_StartUTC":1756823234.17,"Build_Configuration":"Development","Build_IsInternalBuild":false,"Build_IsPerforceBuild":false,"Build_IsPromotedBuild":true,"Build_BranchName":"++ue5+release-5.4","Build_Changelist":35576357,"Hardware_Platform":"Windows","Hardware_GPU":"","Hardware_CPU":"AMD Ryzen 5 9600X 6-Core Processor             ","Hardware_CPU_Cores_Physical":6,"Hardware_CPU_Cores_Logical":12,"Hardware_RAM":66182578176,"Hardware_ComputerName":"MVAT4","Config_IsEditor":true,"Config_IsUnattended":false,"Config_IsBuildMachine":false,"Config_IsRunningCommandlet":false,"Config_IsDebuggerPresent":false,"MapName":"None","SchemaVersion":3,"LoadingName":"BootEditor","AssetType":"DistanceField","Load_Count":35,"Load_TimeSec":0.00773,"Load_SizeMB":3.866115,"Build_Count":0,"Build_TimeSec":0.0,"Build_SizeMB":0.0,"Total_Count":35,"Total_TimeSec":0.00773,"Total_SizeMB":3,"Efficiency":1.0,"Thread_TimeSec":0.007136}
{"EventName":"Core.DDC.Resource","TimestampUTC":1756823239.527000,"RecordId":12,"ProjectName":"WarehouseWreckage","ProjectID":"00000000000000000000000000000000","Session_ID":"{1CA7FCE3-412D-5A25-3428-5294C53E8240}","Session_Label":"","Session_StartUTC":1756823234.17,"Build_Configuration":"Development","Build_IsInternalBuild":false,"Build_IsPerforceBuild":false,"Build_IsPromotedBuild":true,"Build_BranchName":"++ue5+release-5.4","Build_Changelist":35576357,"Hardware_Platform":"Windows","Hardware_GPU":"","Hardware_CPU":"AMD Ryzen 5 9600X 6-Core Processor             ","Hardware_CPU_Cores_Physical":6,"Hardware_CPU_Cores_Logical":12,"Hardware_RAM":66182578176,"Hardware_ComputerName":"MVAT4","Config_IsEditor":true,"Config_IsUnattended":false,"Config_IsBuildMachine":false,"Config_IsRunningCommandlet":false,"Config_IsDebuggerPresent":false,"MapName":"None","SchemaVersion":3,"LoadingName":"BootEditor","AssetType":"Audio (Inline)","Load_Count":8,"Load_TimeSec":0.002669,"Load_SizeMB":0.006736,"Build_Count":0,"Build_TimeSec":0.0,"Build_SizeMB":0.0,"Total_Count":8,"Total_TimeSec":0.002669,"Total_SizeMB":0,"Efficiency":1.0,"Thread_TimeSec":0.002669}
{"EventName":"Core.DDC.Resource","TimestampUTC":1756823239.527000,"RecordId":13,"ProjectName":"WarehouseWreckage","ProjectID":"00000000000000000000000000000000","Session_ID":"{1CA7FCE3-412D-5A25-3428-5294C53E8240}","Session_Label":"","Session_StartUTC":1756823234.17,"Build_Configuration":"Development","Build_IsInternalBuild":false,"Build_IsPerforceBuild":false,"Build_IsPromotedBuild":true,"Build_BranchName":"++ue5+release-5.4","Build_Changelist":35576357,"Hardware_Platform":"Windows","Hardware_GPU":"","Hardware_CPU":"AMD Ryzen 5 9600X 6-Core Processor             ","Hardware_CPU_Cores_Physical":6,"Hardware_CPU_Cores_Logical":12,"Hardware_RAM":66182578176,"Hardware_ComputerName":"MVAT4","Config_IsEditor":true,"Config_IsUnattended":false,"Config_IsBuildMachine":false,"Config_IsRunningCommandlet":false,"Config_IsDebuggerPresent":false,"MapName":"None","SchemaVersion":3,"LoadingName":"BootEditor","AssetType":"NavCollision","Load_Count":35,"Load_TimeSec":0.001413,"Load_SizeMB":0.044932,"Build_Count":0,"Build_TimeSec":0.0,"Build_SizeMB":0.0,"Total_Count":35,"Total_TimeSec":0.001413,"Total_SizeMB":0,"Efficiency":1.0,"Thread_TimeSec":0.001227}
{"EventName":"Core.DDC.Resource","TimestampUTC":1756823239.529000,"RecordId":14,"ProjectName":"WarehouseWreckage","ProjectID":"00000000000000000000000000000000","Session_ID":"{1CA7FCE3-412D-5A25-3428-5294C53E8240}","Session_Label":"","Session_StartUTC":1756823234.17,"Build_Configuration":"Development","Build_IsInternalBuild":false,"Build_IsPerforceBuild":false,"Build_IsPromotedBuild":true,"Build_BranchName":"++ue5+release-5.4","Build_Changelist":35576357,"Hardware_Platform":"Windows","Hardware_GPU":"","Hardware_CPU":"AMD Ryzen 5 9600X 6-Core Processor             ","Hardware_CPU_Cores_Physical":6,"Hardware_CPU_Cores_Logical":12,"Hardware_RAM":66182578176,"Hardware_ComputerName":"MVAT4","Config_IsEditor":true,"Config_IsUnattended":false,"Config_IsBuildMachine":false,"Config_IsRunningCommandlet":false,"Config_IsDebuggerPresent":false,"MapName":"None","SchemaVersion":3,"LoadingName":"BootEditor","AssetType":"Total","Load_Count":627,"Load_TimeSec":0.083823,"Load_SizeMB":194.654664,"Build_Count":0,"Build_TimeSec":0.0,"Build_SizeMB":0.0,"Total_Count":627,"Total_TimeSec":0.083823,"Total_SizeMB":194,"Efficiency":1.0,"Thread_TimeSec":0.08214}
{"EventName":"Core.DDC.Summary","TimestampUTC":1756823239.530000,"RecordId":15,"ProjectName":"WarehouseWreckage","ProjectID":"00000000000000000000000000000000","Session_ID":"{1CA7FCE3-412D-5A25-3428-5294C53E8240}","Session_Label":"","Session_StartUTC":1756823234.17,"Build_Configuration":"Development","Build_IsInternalBuild":false,"Build_IsPerforceBuild":false,"Build_IsPromotedBuild":true,"Build_BranchName":"++ue5+release-5.4","Build_Changelist":35576357,"Hardware_Platform":"Windows","Hardware_GPU":"","Hardware_CPU":"AMD Ryzen 5 9600X 6-Core Processor             ","Hardware_CPU_Cores_Physical":6,"Hardware_CPU_Cores_Logical":12,"Hardware_RAM":66182578176,"Hardware_ComputerName":"MVAT4","Config_IsEditor":true,"Config_IsUnattended":false,"Config_IsBuildMachine":false,"Config_IsRunningCommandlet":false,"Config_IsDebuggerPresent":false,"MapName":"None","SchemaVersion":3,"LoadingName":"BootEditor","BackEnd":"InstalledDerivedDataBackendGraph","HasLocalCache":"true","HasSharedCache":"false","HasCloudCache":"false","HasZenCache":"true","TotalGetHits":892.0,"TotalGetMisses":92.0,"TotalGets":984.0,"TotalGetHitPct":0.906504,"GetMissPct":0.093496,"TotalPutHits":86.0,"TotalPutMisses":0.0,"TotalPuts":86.0,"TotalPutHitPct":1.0,"PutMissPct":0.0,"LocalGetHits":0.0,"LocalGetTotal":0.0,"LocalGetHitPct":0.0,"SharedGetHits":0.0,"SharedGetTotal":0.0,"SharedGetHitPct":0.0,"ZenLocalGetHits":579.0,"ZenLocalGetTotal":671.0,"ZenLocalGetHitPct":0.862891,"ZenRemoteGetHits":0.0,"ZenRemoteGetTotal":0.0,"ZenRemoteGetHitPct":0.0,"CloudGetHits":0.0,"CloudGetTotal":0.0,"CloudGetHitPct":0.0,"LocalLatency":0.0,"LocalReadSpeed":0.0,"LocalWriteSpeed":0.0,"SharedLatency":0.0,"SharedReadSpeed":0.0,"SharedWriteSpeed":0.0,"CloudLatency":0.0,"CloudReadSpeed":0.0,"CloudWriteSpeed":0.0}
{"EventName":"Core.Zen","TimestampUTC":1756823239.531000,"RecordId":16,"ProjectName":"WarehouseWreckage","ProjectID":"00000000000000000000000000000000","Session_ID":"{1CA7FCE3-412D-5A25-3428-5294C53E8240}","Session_Label":"","Session_StartUTC":1756823234.17,"Build_Configuration":"Development","Build_IsInternalBuild":false,"Build_IsPerforceBuild":false,"Build_IsPromotedBuild":true,"Build_BranchName":"++ue5+release-5.4","Build_Changelist":35576357,"Hardware_Platform":"Windows","Hardware_GPU":"","Hardware_CPU":"AMD Ryzen 5 9600X 6-Core Processor             ","Hardware_CPU_Cores_Physical":6,"Hardware_CPU_Cores_Logical":12,"Hardware_RAM":66182578176,"Hardware_ComputerName":"MVAT4","Config_IsEditor":true,"Config_IsUnattended":false,"Config_IsBuildMachine":false,"Config_IsRunningCommandlet":false,"Config_IsDebuggerPresent":false,"MapName":"None","SchemaVersion":1,"LoadingName":"BootEditor","Zen_Enabled":true,"Zen_Cache_Size_Disk":164179663.0,"Zen_Cache_Size_Memory":92616.0,"Zen_Cache_Hits":505,"Zen_Cache_Misses":0,"Zen_Cache_Writes":85,"Zen_Cache_HitRatio":1.0,"Zen_Cache_Cas_Hits":579,"Zen_Cache_Cas_Misses":0,"Zen_Cache_Cas_Writes":0,"Zen_Cache_Requests":590,"Zen_Cache_BadRequests":0,"Zen_Cache_Requests_Count":590,"Zen_Cache_Requests_RateMean":3.964502,"Zen_Cache_Requests_TAverage":0.000041,"Zen_Cache_Requests_TMin":0.000006,"Zen_Cache_Requests_TMax":0.000586,"Zen_Cache_TotalUploadedMB":0.0,"Zen_Upstream_TotalDownloadedMB":0.0,"Zen_Upstream_TotalUploadedMB":0.0,"Zen_Upstream_Requests_Count":0,"Zen_Upstream_Requests_RateMean":0.0,"Zen_Upstream_Requests_TAverage":0.0,"Zen_Upstream_Requests_TMin":0.0,"Zen_Upstream_Requests_TMax":0.0,"Zen_Cas_Size_Large":0,"Zen_Cas_Size_Small":14398188,"Zen_Cas_Size_Tiny":112102,"Zen_Cas_Size_Total":14510290,"Zen_Project_Size_Disk":0.0,"Zen_Project_Size_Memory":0.0,"Zen_Project_WriteCount":0,"Zen_Project_ReadCount":0,"Zen_Project_DeleteCount":0,"Zen_Project_Oplog_WriteCount":0,"Zen_Project_Oplog_ReadCount":0,"Zen_Project_Oplog_DeleteCount":0,"Zen_Project_Op_Hits":0,"Zen_Project_Op_Misses":0,"Zen_Project_Op_Writes":0,"Zen_Project_Chunk_Hits":0,"Zen_Project_Chunk_Misses":0,"Zen_Project_Chunk_Writes":0,"Zen_Project_Requests":0,"Zen_Project_BadRequests":0,"Zen_Project_Op_HitRatio":0.0,"Zen_Project_Chunk_HitRatio":0.0}
{"EventName":"Span","TimestampUTC":1756823240.302000,"RecordId":17,"ProjectName":"WarehouseWreckage","ProjectID":"00000000000000000000000000000000","Session_ID":"{1CA7FCE3-412D-5A25-3428-5294C53E8240}","Session_Label":"","Session_StartUTC":1756823234.17,"Build_Configuration":"Development","Build_IsInternalBuild":false,"Build_IsPerforceBuild":false,"Build_IsPromotedBuild":true,"Build_BranchName":"++ue5+release-5.4","Build_Changelist":35576357,"Hardware_Platform":"Windows","Hardware_GPU":"","Hardware_CPU":"AMD Ryzen 5 9600X 6-Core Processor             ","Hardware_CPU_Cores_Physical":6,"Hardware_CPU_Cores_Logical":12,"Hardware_RAM":66182578176,"Hardware_ComputerName":"MVAT4","Config_IsEditor":true,"Config_IsUnattended":false,"Config_IsBuildMachine":false,"Config_IsRunningCommandlet":false,"Config_IsDebuggerPresent":false,"MapName":"None","TaskName":"Saving packages...","SchemaVersion":1,"Span_Name":"ST Saving packages...","Span_GUID":"2BBB224D4B8567EA342E84BD1F57DEE3","Span_ParentName":"Editor.Initialize","Span_ThreadId":30336,"Span_Depth":3,"Span_StartUTC":1756823239.968,"Span_EndUTC":1756823240.302,"Span_TimeInSec":0.334}
{"EventName":"Span","TimestampUTC":1756823240.835000,"RecordId":18,"ProjectName":"WarehouseWreckage","ProjectID":"00000000000000000000000000000000","Session_ID":"{1CA7FCE3-412D-5A25-3428-5294C53E8240}","Session_Label":"","Session_StartUTC":1756823234.17,"Build_Configuration":"Development","Build_IsInternalBuild":false,"Build_IsPerforceBuild":false,"Build_IsPromotedBuild":true,"Build_BranchName":"++ue5+release-5.4","Build_Changelist":35576357,"Hardware_Platform":"Windows","Hardware_GPU":"","Hardware_CPU":"AMD Ryzen 5 9600X 6-Core Processor             ","Hardware_CPU_Cores_Physical":6,"Hardware_CPU_Cores_Logical":12,"Hardware_RAM":66182578176,"Hardware_ComputerName":"MVAT4","Config_IsEditor":true,"Config_IsUnattended":false,"Config_IsBuildMachine":false,"Config_IsRunningCommandlet":false,"Config_IsDebuggerPresent":false,"MapName":"OpenWorld","SchemaVersion":1,"Span_Name":"Editor.LoadMap","Span_GUID":"550D7CEA464F4F5F3FD8C8901A480F3B","Span_ParentName":"Editor","Span_ThreadId":30336,"Span_Depth":3,"Span_StartUTC":1756823240.306,"Span_EndUTC":1756823240.835,"Span_TimeInSec":0.529}
{"EventName":"Core.Loading","TimestampUTC":1756823240.836000,"RecordId":19,"ProjectName":"WarehouseWreckage","ProjectID":"00000000000000000000000000000000","Session_ID":"{1CA7FCE3-412D-5A25-3428-5294C53E8240}","Session_Label":"","Session_StartUTC":1756823234.17,"Build_Configuration":"Development","Build_IsInternalBuild":false,"Build_IsPerforceBuild":false,"Build_IsPromotedBuild":true,"Build_BranchName":"++ue5+release-5.4","Build_Changelist":35576357,"Hardware_Platform":"Windows","Hardware_GPU":"","Hardware_CPU":"AMD Ryzen 5 9600X 6-Core Processor             ","Hardware_CPU_Cores_Physical":6,"Hardware_CPU_Cores_Logical":12,"Hardware_RAM":66182578176,"Hardware_ComputerName":"MVAT4","Config_IsEditor":true,"Config_IsUnattended":false,"Config_IsBuildMachine":false,"Config_IsRunningCommandlet":false,"Config_IsDebuggerPresent":false,"MapName":"OpenWorld","SchemaVersion":3,"LoadingName":"LoadMap","LoadingSeconds":0.529,"Zen_Enabled":true,"Zen_Cache_Size_Disk":164179663.0,"Zen_Cache_Size_Memory":92616.0,"Zen_Cache_Hits":505,"Zen_Cache_Misses":0,"Zen_Cache_Writes":85,"Zen_Cache_HitRatio":1.0,"Zen_Cache_Cas_Hits":579,"Zen_Cache_Cas_Misses":0,"Zen_Cache_Cas_Writes":0,"Zen_Cache_Requests":590,"Zen_Cache_BadRequests":0,"Zen_Cache_Requests_Count":590,"Zen_Cache_Requests_RateMean":3.964502,"Zen_Cache_Requests_TAverage":0.000041,"Zen_Cache_Requests_TMin":0.000006,"Zen_Cache_Requests_TMax":0.000586,"Zen_Cache_TotalUploadedMB":0.0,"Zen_Upstream_TotalDownloadedMB":0.0,"Zen_Upstream_TotalUploadedMB":0.0,"Zen_Upstream_Requests_Count":0,"Zen_Upstream_Requests_RateMean":0.0,"Zen_Upstream_Requests_TAverage":0.0,"Zen_Upstream_Requests_TMin":0.0,"Zen_Upstream_Requests_TMax":0.0,"Zen_Cas_Size_Large":0,"Zen_Cas_Size_Small":14398188,"Zen_Cas_Size_Tiny":112102,"Zen_Cas_Size_Total":14510290,"Zen_Project_Size_Disk":0.0,"Zen_Project_Size_Memory":0.0,"Zen_Project_WriteCount":0,"Zen_Project_ReadCount":0,"Zen_Project_DeleteCount":0,"Zen_Project_Oplog_WriteCount":0,"Zen_Project_Oplog_ReadCount":0,"Zen_Project_Oplog_DeleteCount":0,"Zen_Project_Op_Hits":0,"Zen_Project_Op_Misses":0,"Zen_Project_Op_Writes":0,"Zen_Project_Chunk_Hits":0,"Zen_Project_Chunk_Misses":0,"Zen_Project_Chunk_Writes":0,"Zen_Project_Requests":0,"Zen_Project_BadRequests":0,"Zen_Project_Op_HitRatio":0.0,"Zen_Project_Chunk_HitRatio":0.0,"DDC_Summary_BackEnd":"InstalledDerivedDataBackendGraph","DDC_Summary_HasLocalCache":"true","DDC_Summary_HasSharedCache":"false","DDC_Summary_HasCloudCache":"false","DDC_Summary_HasZenCache":"true","DDC_Summary_TotalGetHits":1708.0,"DDC_Summary_TotalGetMisses":94.0,"DDC_Summary_TotalGets":1802.0,"DDC_Summary_TotalGetHitPct":0.947836,"DDC_Summary_GetMissPct":0.052164,"DDC_Summary_TotalPutHits":88.0,"DDC_Summary_TotalPutMisses":0.0,"DDC_Summary_TotalPuts":88.0,"DDC_Summary_TotalPutHitPct":1.0,"DDC_Summary_PutMissPct":0.0,"DDC_Summary_LocalGetHits":0.0,"DDC_Summary_LocalGetTotal":0.0,"DDC_Summary_LocalGetHitPct":0.0,"DDC_Summary_SharedGetHits":0.0,"DDC_Summary_SharedGetTotal":0.0,"DDC_Summary_SharedGetHitPct":0.0,"DDC_Summary_ZenLocalGetHits":600.0,"DDC_Summary_ZenLocalGetTotal":693.0,"DDC_Summary_ZenLocalGetHitPct":0.865801,"DDC_Summary_ZenRemoteGetHits":0.0,"DDC_Summary_ZenRemoteGetTotal":0.0,"DDC_Summary_ZenRemoteGetHitPct":0.0,"DDC_Summary_CloudGetHits":0.0,"DDC_Summary_CloudGetTotal":0.0,"DDC_Summary_CloudGetHitPct":0.0,"DDC_Summary_LocalLatency":0.0,"DDC_Summary_LocalReadSpeed":0.0,"DDC_Summary_LocalWriteSpeed":0.0,"DDC_Summary_SharedLatency":0.0,"DDC_Summary_SharedReadSpeed":0.0,"DDC_Summary_SharedWriteSpeed":0.0,"DDC_Summary_CloudLatency":0.0,"DDC_Summary_CloudReadSpeed":0.0,"DDC_Summary_CloudWriteSpeed":0.0}
{"EventName":"Core.DDC.Resource","TimestampUTC":1756823240.837000,"RecordId":20,"ProjectName":"WarehouseWreckage","ProjectID":"00000000000000000000000000000000","Session_ID":"{1CA7FCE3-412D-5A25-3428-5294C53E8240}","Session_Label":"","Session_StartUTC":1756823234.17,"Build_Configuration":"Development","Build_IsInternalBuild":false,"Build_IsPerforceBuild":false,"Build_IsPromotedBuild":true,"Build_BranchName":"++ue5+release-5.4","Build_Changelist":35576357,"Hardware_Platform":"Windows","Hardware_GPU":"","Hardware_CPU":"AMD Ryzen 5 9600X 6-Core Processor             ","Hardware_CPU_Cores_Physical":6,"Hardware_CPU_Cores_Logical":12,"Hardware_RAM":66182578176,"Hardware_ComputerName":"MVAT4","Config_IsEditor":true,"Config_IsUnattended":false,"Config_IsBuildMachine":false,"Config_IsRunningCommandlet":false,"Config_IsDebuggerPresent":false,"MapName":"OpenWorld","SchemaVersion":3,"LoadingName":"LoadMap","AssetType":"Texture (Inline)","Load_Count":124,"Load_TimeSec":0.011366,"Load_SizeMB":84.999616,"Build_Count":0,"Build_TimeSec":0.0,"Build_SizeMB":0.0,"Total_Count":124,"Total_TimeSec":0.011366,"Total_SizeMB":84,"Efficiency":1.0,"Thread_TimeSec":0.011366}
{"EventName":"Core.DDC.Resource","TimestampUTC":1756823240.838000,"RecordId":21,"ProjectName":"WarehouseWreckage","ProjectID":"00000000000000000000000000000000","Session_ID":"{1CA7FCE3-412D-5A25-3428-5294C53E8240}","Session_Label":"","Session_StartUTC":1756823234.17,"Build_Configuration":"Development","Build_IsInternalBuild":false,"Build_IsPerforceBuild":false,"Build_IsPromotedBuild":true,"Build_BranchName":"++ue5+release-5.4","Build_Changelist":35576357,"Hardware_Platform":"Windows","Hardware_GPU":"","Hardware_CPU":"AMD Ryzen 5 9600X 6-Core Processor             ","Hardware_CPU_Cores_Physical":6,"Hardware_CPU_Cores_Logical":12,"Hardware_RAM":66182578176,"Hardware_ComputerName":"MVAT4","Config_IsEditor":true,"Config_IsUnattended":false,"Config_IsBuildMachine":false,"Config_IsRunningCommandlet":false,"Config_IsDebuggerPresent":false,"MapName":"OpenWorld","SchemaVersion":3,"LoadingName":"LoadMap","AssetType":"Texture (Streaming)","Load_Count":32,"Load_TimeSec":0.003793,"Load_SizeMB":9.146484,"Build_Count":0,"Build_TimeSec":0.0,"Build_SizeMB":0.0,"Total_Count":32,"Total_TimeSec":0.003793,"Total_SizeMB":9,"Efficiency":1.0,"Thread_TimeSec":0.003793}
{"EventName":"Core.DDC.Resource","TimestampUTC":1756823240.839000,"RecordId":22,"ProjectName":"WarehouseWreckage","ProjectID":"00000000000000000000000000000000","Session_ID":"{1CA7FCE3-412D-5A25-3428-5294C53E8240}","Session_Label":"","Session_StartUTC":1756823234.17,"Build_Configuration":"Development","Build_IsInternalBuild":false,"Build_IsPerforceBuild":false,"Build_IsPromotedBuild":true,"Build_BranchName":"++ue5+release-5.4","Build_Changelist":35576357,"Hardware_Platform":"Windows","Hardware_GPU":"","Hardware_CPU":"AMD Ryzen 5 9600X 6-Core Processor             ","Hardware_CPU_Cores_Physical":6,"Hardware_CPU_Cores_Logical":12,"Hardware_RAM":66182578176,"Hardware_ComputerName":"MVAT4","Config_IsEditor":true,"Config_IsUnattended":false,"Config_IsBuildMachine":false,"Config_IsRunningCommandlet":false,"Config_IsDebuggerPresent":false,"MapName":"OpenWorld","SchemaVersion":3,"LoadingName":"LoadMap","AssetType":"StaticMesh","Load_Count":38,"Load_TimeSec":0.008605,"Load_SizeMB":4.451952,"Build_Count":0,"Build_TimeSec":0.0,"Build_SizeMB":0.0,"Total_Count":38,"Total_TimeSec":0.008605,"Total_SizeMB":4,"Efficiency":1.0,"Thread_TimeSec":0.006869}
{"EventName":"Core.DDC.Resource","TimestampUTC":1756823240.839000,"RecordId":23,"ProjectName":"WarehouseWreckage","ProjectID":"00000000000000000000000000000000","Session_ID":"{1CA7FCE3-412D-5A25-3428-5294C53E8240}","Session_Label":"","Session_StartUTC":1756823234.17,"Build_Configuration":"Development","Build_IsInternalBuild":false,"Build_IsPerforceBuild":false,"Build_IsPromotedBuild":true,"Build_BranchName":"++ue5+release-5.4","Build_Changelist":35576357,"Hardware_Platform":"Windows","Hardware_GPU":"","Hardware_CPU":"AMD Ryzen 5 9600X 6-Core Processor             ","Hardware_CPU_Cores_Physical":6,"Hardware_CPU_Cores_Logical":12,"Hardware_RAM":66182578176,"Hardware_ComputerName":"MVAT4","Config_IsEditor":true,"Config_IsUnattended":false,"Config_IsBuildMachine":false,"Config_IsRunningCommandlet":false,"Config_IsDebuggerPresent":false,"MapName":"OpenWorld","SchemaVersion":3,"LoadingName":"LoadMap","AssetType":"GlobalShader","Load_Count":346,"Load_TimeSec":0.03925,"Load_SizeMB":106.153169,"Build_Count":0,"Build_TimeSec":0.0,"Build_SizeMB":0.0,"Total_Count":346,"Total_TimeSec":0.03925,"Total_SizeMB":106,"Efficiency":1.0,"Thread_TimeSec":0.03925}
{"EventName":"Core.DDC.Resource","TimestampUTC":1756823240.840000,"RecordId":24,"ProjectName":"WarehouseWreckage","ProjectID":"00000000000000000000000000000000","Session_ID":"{1CA7FCE3-412D-5A25-3428-5294C53E8240}","Session_Label":"","Session_StartUTC":1756823234.17,"Build_Configuration":"Development","Build_IsInternalBuild":false,"Build_IsPerforceBuild":false,"Build_IsPromotedBuild":true,"Build_BranchName":"++ue5+release-5.4","Build_Changelist":35576357,"Hardware_Platform":"Windows","Hardware_GPU":"","Hardware_CPU":"AMD Ryzen 5 9600X 6-Core Processor             ","Hardware_CPU_Cores_Physical":6,"Hardware_CPU_Cores_Logical":12,"Hardware_RAM":66182578176,"Hardware_ComputerName":"MVAT4","Config_IsEditor":true,"Config_IsUnattended":false,"Config_IsBuildMachine":false,"Config_IsRunningCommandlet":false,"Config_IsDebuggerPresent":false,"MapName":"OpenWorld","SchemaVersion":3,"LoadingName":"LoadMap","AssetType":"BodySetup","Load_Count":1,"Load_TimeSec":0.001331,"Load_SizeMB":1.456863,"Build_Count":0,"Build_TimeSec":0.0,"Build_SizeMB":0.0,"Total_Count":1,"Total_TimeSec":0.001331,"Total_SizeMB":1,"Efficiency":1.0,"Thread_TimeSec":0.001331}
{"EventName":"Core.DDC.Resource","TimestampUTC":1756823240.841000,"RecordId":25,"ProjectName":"WarehouseWreckage","ProjectID":"00000000000000000000000000000000","Session_ID":"{1CA7FCE3-412D-5A25-3428-5294C53E8240}","Session_Label":"","Session_StartUTC":1756823234.17,"Build_Configuration":"Development","Build_IsInternalBuild":false,"Build_IsPerforceBuild":false,"Build_IsPromotedBuild":true,"Build_BranchName":"++ue5+release-5.4","Build_Changelist":35576357,"Hardware_Platform":"Windows","Hardware_GPU":"","Hardware_CPU":"AMD Ryzen 5 9600X 6-Core Processor             ","Hardware_CPU_Cores_Physical":6,"Hardware_CPU_Cores_Logical":12,"Hardware_RAM":66182578176,"Hardware_ComputerName":"MVAT4","Config_IsEditor":true,"Config_IsUnattended":false,"Config_IsBuildMachine":false,"Config_IsRunningCommandlet":false,"Config_IsDebuggerPresent":false,"MapName":"OpenWorld","SchemaVersion":3,"LoadingName":"LoadMap","AssetType":"CardRepresentation","Load_Count":38,"Load_TimeSec":0.002367,"Load_SizeMB":0.01085,"Build_Count":0,"Build_TimeSec":0.0,"Build_SizeMB":0.0,"Total_Count":38,"Total_TimeSec":0.002367,"Total_SizeMB":0,"Efficiency":1.0,"Thread_TimeSec":0.001906}
{"EventName":"Core.DDC.Resource","TimestampUTC":1756823240.842000,"RecordId":26,"ProjectName":"WarehouseWreckage","ProjectID":"00000000000000000000000000000000","Session_ID":"{1CA7FCE3-412D-5A25-3428-5294C53E8240}","Session_Label":"","Session_StartUTC":1756823234.17,"Build_Configuration":"Development","Build_IsInternalBuild":false,"Build_IsPerforceBuild":false,"Build_IsPromotedBuild":true,"Build_BranchName":"++ue5+release-5.4","Build_Changelist":35576357,"Hardware_Platform":"Windows","Hardware_GPU":"","Hardware_CPU":"AMD Ryzen 5 9600X 6-Core Processor             ","Hardware_CPU_Cores_Physical":6,"Hardware_CPU_Cores_Logical":12,"Hardware_RAM":66182578176,"Hardware_ComputerName":"MVAT4","Config_IsEditor":true,"Config_IsUnattended":false,"Config_IsBuildMachine":false,"Config_IsRunningCommandlet":false,"Config_IsDebuggerPresent":false,"MapName":"OpenWorld","SchemaVersion":3,"LoadingName":"LoadMap","AssetType":"MaterialShader","Load_Count":4,"Load_TimeSec":0.00698,"Load_SizeMB":17.932115,"Build_Count":0,"Build_TimeSec":0.0,"Build_SizeMB":0.0,"Total_Count":4,"Total_TimeSec":0.00698,"Total_SizeMB":17,"Efficiency":1.0,"Thread_TimeSec":0.00698}
{"EventName":"Core.DDC.Resource","TimestampUTC":1756823240.843000,"RecordId":27,"ProjectName":"WarehouseWreckage","ProjectID":"00000000000000000000000000000000","Session_ID":"{1CA7FCE3-412D-5A25-3428-5294C53E8240}","Session_Label":"","Session_StartUTC":1756823234.17,"Build_Configuration":"Development","Build_IsInternalBuild":false,"Build_IsPerforceBuild":false,"Build_IsPromotedBuild":true,"Build_BranchName":"++ue5+release-5.4","Build_Changelist":35576357,"Hardware_Platform":"Windows","Hardware_GPU":"","Hardware_CPU":"AMD Ryzen 5 9600X 6-Core Processor             ","Hardware_CPU_Cores_Physical":6,"Hardware_CPU_Cores_Logical":12,"Hardware_RAM":66182578176,"Hardware_ComputerName":"MVAT4","Config_IsEditor":true,"Config_IsUnattended":false,"Config_IsBuildMachine":false,"Config_IsRunningCommandlet":false,"Config_IsDebuggerPresent":false,"MapName":"OpenWorld","SchemaVersion":3,"LoadingName":"LoadMap","AssetType":"DistanceField","Load_Count":38,"Load_TimeSec":0.00999,"Load_SizeMB":5.889612,"Build_Count":0,"Build_TimeSec":0.0,"Build_SizeMB":0.0,"Total_Count":38,"Total_TimeSec":0.00999,"Total_SizeMB":5,"Efficiency":1.0,"Thread_TimeSec":0.007136}
{"EventName":"Core.DDC.Resource","TimestampUTC":1756823240.843000,"RecordId":28,"ProjectName":"WarehouseWreckage","ProjectID":"00000000000000000000000000000000","Session_ID":"{1CA7FCE3-412D-5A25-3428-5294C53E8240}","Session_Label":"","Session_StartUTC":1756823234.17,"Build_Configuration":"Development","Build_IsInternalBuild":false,"Build_IsPerforceBuild":false,"Build_IsPromotedBuild":true,"Build_BranchName":"++ue5+release-5.4","Build_Changelist":35576357,"Hardware_Platform":"Windows","Hardware_GPU":"","Hardware_CPU":"AMD Ryzen 5 9600X 6-Core Processor             ","Hardware_CPU_Cores_Physical":6,"Hardware_CPU_Cores_Logical":12,"Hardware_RAM":66182578176,"Hardware_ComputerName":"MVAT4","Config_IsEditor":true,"Config_IsUnattended":false,"Config_IsBuildMachine":false,"Config_IsRunningCommandlet":false,"Config_IsDebuggerPresent":false,"MapName":"OpenWorld","SchemaVersion":3,"LoadingName":"LoadMap","AssetType":"Audio (Inline)","Load_Count":8,"Load_TimeSec":0.002669,"Load_SizeMB":0.006736,"Build_Count":0,"Build_TimeSec":0.0,"Build_SizeMB":0.0,"Total_Count":8,"Total_TimeSec":0.002669,"Total_SizeMB":0,"Efficiency":1.0,"Thread_TimeSec":0.002669}
{"EventName":"Core.DDC.Resource","TimestampUTC":1756823240.844000,"RecordId":29,"ProjectName":"WarehouseWreckage","ProjectID":"00000000000000000000000000000000","Session_ID":"{1CA7FCE3-412D-5A25-3428-5294C53E8240}","Session_Label":"","Session_StartUTC":1756823234.17,"Build_Configuration":"Development","Build_IsInternalBuild":false,"Build_IsPerforceBuild":false,"Build_IsPromotedBuild":true,"Build_BranchName":"++ue5+release-5.4","Build_Changelist":35576357,"Hardware_Platform":"Windows","Hardware_GPU":"","Hardware_CPU":"AMD Ryzen 5 9600X 6-Core Processor             ","Hardware_CPU_Cores_Physical":6,"Hardware_CPU_Cores_Logical":12,"Hardware_RAM":66182578176,"Hardware_ComputerName":"MVAT4","Config_IsEditor":true,"Config_IsUnattended":false,"Config_IsBuildMachine":false,"Config_IsRunningCommandlet":false,"Config_IsDebuggerPresent":false,"MapName":"OpenWorld","SchemaVersion":3,"LoadingName":"LoadMap","AssetType":"LandscapeCollision (Heightfield)","Load_Count":0,"Load_TimeSec":0.0,"Load_SizeMB":0.0,"Build_Count":512,"Build_TimeSec":0.198202,"Build_SizeMB":24.52832,"Total_Count":512,"Total_TimeSec":0.198202,"Total_SizeMB":24,"Efficiency":0.0,"Thread_TimeSec":0.198202}
{"EventName":"Core.DDC.Resource","TimestampUTC":1756823240.845000,"RecordId":30,"ProjectName":"WarehouseWreckage","ProjectID":"00000000000000000000000000000000","Session_ID":"{1CA7FCE3-412D-5A25-3428-5294C53E8240}","Session_Label":"","Session_StartUTC":1756823234.17,"Build_Configuration":"Development","Build_IsInternalBuild":false,"Build_IsPerforceBuild":false,"Build_IsPromotedBuild":true,"Build_BranchName":"++ue5+release-5.4","Build_Changelist":35576357,"Hardware_Platform":"Windows","Hardware_GPU":"","Hardware_CPU":"AMD Ryzen 5 9600X 6-Core Processor             ","Hardware_CPU_Cores_Physical":6,"Hardware_CPU_Cores_Logical":12,"Hardware_RAM":66182578176,"Hardware_ComputerName":"MVAT4","Config_IsEditor":true,"Config_IsUnattended":false,"Config_IsBuildMachine":false,"Config_IsRunningCommandlet":false,"Config_IsDebuggerPresent":false,"MapName":"OpenWorld","SchemaVersion":3,"LoadingName":"LoadMap","AssetType":"NavCollision","Load_Count":37,"Load_TimeSec":0.001489,"Load_SizeMB":0.046027,"Build_Count":0,"Build_TimeSec":0.0,"Build_SizeMB":0.0,"Total_Count":37,"Total_TimeSec":0.001489,"Total_SizeMB":0,"Efficiency":1.0,"Thread_TimeSec":0.001227}
{"EventName":"Core.DDC.Resource","TimestampUTC":1756823240.845000,"RecordId":31,"ProjectName":"WarehouseWreckage","ProjectID":"00000000000000000000000000000000","Session_ID":"{1CA7FCE3-412D-5A25-3428-5294C53E8240}","Session_Label":"","Session_StartUTC":1756823234.17,"Build_Configuration":"Development","Build_IsInternalBuild":false,"Build_IsPerforceBuild":false,"Build_IsPromotedBuild":true,"Build_BranchName":"++ue5+release-5.4","Build_Changelist":35576357,"Hardware_Platform":"Windows","Hardware_GPU":"","Hardware_CPU":"AMD Ryzen 5 9600X 6-Core Processor             ","Hardware_CPU_Cores_Physical":6,"Hardware_CPU_Cores_Logical":12,"Hardware_RAM":66182578176,"Hardware_ComputerName":"MVAT4","Config_IsEditor":true,"Config_IsUnattended":false,"Config_IsBuildMachine":false,"Config_IsRunningCommandlet":false,"Config_IsDebuggerPresent":false,"MapName":"OpenWorld","SchemaVersion":3,"LoadingName":"LoadMap","AssetType":"Total","Load_Count":666,"Load_TimeSec":0.08784,"Load_SizeMB":230.093424,"Build_Count":512,"Build_TimeSec":0.198202,"Build_SizeMB":24.52832,"Total_Count":1178,"Total_TimeSec":0.286042,"Total_SizeMB":254,"Efficiency":0.565365,"Thread_TimeSec":0.280729}
{"EventName":"Core.DDC.Summary","TimestampUTC":1756823240.847000,"RecordId":32,"ProjectName":"WarehouseWreckage","ProjectID":"00000000000000000000000000000000","Session_ID":"{1CA7FCE3-412D-5A25-3428-5294C53E8240}","Session_Label":"","Session_StartUTC":1756823234.17,"Build_Configuration":"Development","Build_IsInternalBuild":false,"Build_IsPerforceBuild":false,"Build_IsPromotedBuild":true,"Build_BranchName":"++ue5+release-5.4","Build_Changelist":35576357,"Hardware_Platform":"Windows","Hardware_GPU":"","Hardware_CPU":"AMD Ryzen 5 9600X 6-Core Processor             ","Hardware_CPU_Cores_Physical":6,"Hardware_CPU_Cores_Logical":12,"Hardware_RAM":66182578176,"Hardware_ComputerName":"MVAT4","Config_IsEditor":true,"Config_IsUnattended":false,"Config_IsBuildMachine":false,"Config_IsRunningCommandlet":false,"Config_IsDebuggerPresent":false,"MapName":"OpenWorld","SchemaVersion":3,"LoadingName":"LoadMap","BackEnd":"InstalledDerivedDataBackendGraph","HasLocalCache":"true","HasSharedCache":"false","HasCloudCache":"false","HasZenCache":"true","TotalGetHits":1708.0,"TotalGetMisses":94.0,"TotalGets":1802.0,"TotalGetHitPct":0.947836,"GetMissPct":0.052164,"TotalPutHits":88.0,"TotalPutMisses":0.0,"TotalPuts":88.0,"TotalPutHitPct":1.0,"PutMissPct":0.0,"LocalGetHits":0.0,"LocalGetTotal":0.0,"LocalGetHitPct":0.0,"SharedGetHits":0.0,"SharedGetTotal":0.0,"SharedGetHitPct":0.0,"ZenLocalGetHits":600.0,"ZenLocalGetTotal":693.0,"ZenLocalGetHitPct":0.865801,"ZenRemoteGetHits":0.0,"ZenRemoteGetTotal":0.0,"ZenRemoteGetHitPct":0.0,"CloudGetHits":0.0,"CloudGetTotal":0.0,"CloudGetHitPct":0.0,"LocalLatency":0.0,"LocalReadSpeed":0.0,"LocalWriteSpeed":0.0,"SharedLatency":0.0,"SharedReadSpeed":0.0,"SharedWriteSpeed":0.0,"CloudLatency":0.0,"CloudReadSpeed":0.0,"CloudWriteSpeed":0.0}
{"EventName":"Core.Zen","TimestampUTC":1756823240.847000,"RecordId":33,"ProjectName":"WarehouseWreckage","ProjectID":"00000000000000000000000000000000","Session_ID":"{1CA7FCE3-412D-5A25-3428-5294C53E8240}","Session_Label":"","Session_StartUTC":1756823234.17,"Build_Configuration":"Development","Build_IsInternalBuild":false,"Build_IsPerforceBuild":false,"Build_IsPromotedBuild":true,"Build_BranchName":"++ue5+release-5.4","Build_Changelist":35576357,"Hardware_Platform":"Windows","Hardware_GPU":"","Hardware_CPU":"AMD Ryzen 5 9600X 6-Core Processor             ","Hardware_CPU_Cores_Physical":6,"Hardware_CPU_Cores_Logical":12,"Hardware_RAM":66182578176,"Hardware_ComputerName":"MVAT4","Config_IsEditor":true,"Config_IsUnattended":false,"Config_IsBuildMachine":false,"Config_IsRunningCommandlet":false,"Config_IsDebuggerPresent":false,"MapName":"OpenWorld","SchemaVersion":1,"LoadingName":"LoadMap","Zen_Enabled":true,"Zen_Cache_Size_Disk":164202191.0,"Zen_Cache_Size_Memory":132856.0,"Zen_Cache_Hits":1190,"Zen_Cache_Misses":6,"Zen_Cache_Writes":173,"Zen_Cache_HitRatio":0.994983,"Zen_Cache_Cas_Hits":1070,"Zen_Cache_Cas_Misses":0,"Zen_Cache_Cas_Writes":0,"Zen_Cache_Requests":1051,"Zen_Cache_BadRequests":0,"Zen_Cache_Requests_Count":1051,"Zen_Cache_Requests_RateMean":6.806388,"Zen_Cache_Requests_TAverage":0.000057,"Zen_Cache_Requests_TMin":0.000006,"Zen_Cache_Requests_TMax":0.001146,"Zen_Cache_TotalUploadedMB":0.0,"Zen_Upstream_TotalDownloadedMB":0.0,"Zen_Upstream_TotalUploadedMB":0.0,"Zen_Upstream_Requests_Count":0,"Zen_Upstream_Requests_RateMean":0.0,"Zen_Upstream_Requests_TAverage":0.0,"Zen_Upstream_Requests_TMin":0.0,"Zen_Upstream_Requests_TMax":0.0,"Zen_Cas_Size_Large":0,"Zen_Cas_Size_Small":14398188,"Zen_Cas_Size_Tiny":112102,"Zen_Cas_Size_Total":14510290,"Zen_Project_Size_Disk":0.0,"Zen_Project_Size_Memory":0.0,"Zen_Project_WriteCount":0,"Zen_Project_ReadCount":0,"Zen_Project_DeleteCount":0,"Zen_Project_Oplog_WriteCount":0,"Zen_Project_Oplog_ReadCount":0,"Zen_Project_Oplog_DeleteCount":0,"Zen_Project_Op_Hits":0,"Zen_Project_Op_Misses":0,"Zen_Project_Op_Writes":0,"Zen_Project_Chunk_Hits":0,"Zen_Project_Chunk_Misses":0,"Zen_Project_Chunk_Writes":0,"Zen_Project_Requests":0,"Zen_Project_BadRequests":0,"Zen_Project_Op_HitRatio":0.0,"Zen_Project_Chunk_HitRatio":0.0}
{"EventName":"Span","TimestampUTC":1756823240.854000,"RecordId":34,"ProjectName":"WarehouseWreckage","ProjectID":"00000000000000000000000000000000","Session_ID":"{1CA7FCE3-412D-5A25-3428-5294C53E8240}","Session_Label":"","Session_StartUTC":1756823234.17,"Build_Configuration":"Development","Build_IsInternalBuild":false,"Build_IsPerforceBuild":false,"Build_IsPromotedBuild":true,"Build_BranchName":"++ue5+release-5.4","Build_Changelist":35576357,"Hardware_Platform":"Windows","Hardware_GPU":"","Hardware_CPU":"AMD Ryzen 5 9600X 6-Core Processor             ","Hardware_CPU_Cores_Physical":6,"Hardware_CPU_Cores_Logical":12,"Hardware_RAM":66182578176,"Hardware_ComputerName":"MVAT4","Config_IsEditor":true,"Config_IsUnattended":false,"Config_IsBuildMachine":false,"Config_IsRunningCommandlet":false,"Config_IsDebuggerPresent":false,"MapName":"OpenWorld","SchemaVersion":1,"Span_Name":"Editor.Initialize","Span_GUID":"63751D5B49C03261691D3EB601FD91BE","Span_ParentName":"Editor","Span_ThreadId":30336,"Span_Depth":2,"Span_StartUTC":1756823239.532,"Span_EndUTC":1756823240.854,"Span_TimeInSec":1.322}
{"EventName":"Core.Loading","TimestampUTC":1756823240.855000,"RecordId":35,"ProjectName":"WarehouseWreckage","ProjectID":"00000000000000000000000000000000","Session_ID":"{1CA7FCE3-412D-5A25-3428-5294C53E8240}","Session_Label":"","Session_StartUTC":1756823234.17,"Build_Configuration":"Development","Build_IsInternalBuild":false,"Build_IsPerforceBuild":false,"Build_IsPromotedBuild":true,"Build_BranchName":"++ue5+release-5.4","Build_Changelist":35576357,"Hardware_Platform":"Windows","Hardware_GPU":"","Hardware_CPU":"AMD Ryzen 5 9600X 6-Core Processor             ","Hardware_CPU_Cores_Physical":6,"Hardware_CPU_Cores_Logical":12,"Hardware_RAM":66182578176,"Hardware_ComputerName":"MVAT4","Config_IsEditor":true,"Config_IsUnattended":false,"Config_IsBuildMachine":false,"Config_IsRunningCommandlet":false,"Config_IsDebuggerPresent":false,"MapName":"OpenWorld","SchemaVersion":3,"LoadingName":"TotalEditorStartup","LoadingSeconds":7.259749,"Zen_Enabled":true,"Zen_Cache_Size_Disk":164202191.0,"Zen_Cache_Size_Memory":132856.0,"Zen_Cache_Hits":1190,"Zen_Cache_Misses":6,"Zen_Cache_Writes":173,"Zen_Cache_HitRatio":0.994983,"Zen_Cache_Cas_Hits":1070,"Zen_Cache_Cas_Misses":0,"Zen_Cache_Cas_Writes":0,"Zen_Cache_Requests":1051,"Zen_Cache_BadRequests":0,"Zen_Cache_Requests_Count":1051,"Zen_Cache_Requests_RateMean":6.806388,"Zen_Cache_Requests_TAverage":0.000057,"Zen_Cache_Requests_TMin":0.000006,"Zen_Cache_Requests_TMax":0.001146,"Zen_Cache_TotalUploadedMB":0.0,"Zen_Upstream_TotalDownloadedMB":0.0,"Zen_Upstream_TotalUploadedMB":0.0,"Zen_Upstream_Requests_Count":0,"Zen_Upstream_Requests_RateMean":0.0,"Zen_Upstream_Requests_TAverage":0.0,"Zen_Upstream_Requests_TMin":0.0,"Zen_Upstream_Requests_TMax":0.0,"Zen_Cas_Size_Large":0,"Zen_Cas_Size_Small":14398188,"Zen_Cas_Size_Tiny":112102,"Zen_Cas_Size_Total":14510290,"Zen_Project_Size_Disk":0.0,"Zen_Project_Size_Memory":0.0,"Zen_Project_WriteCount":0,"Zen_Project_ReadCount":0,"Zen_Project_DeleteCount":0,"Zen_Project_Oplog_WriteCount":0,"Zen_Project_Oplog_ReadCount":0,"Zen_Project_Oplog_DeleteCount":0,"Zen_Project_Op_Hits":0,"Zen_Project_Op_Misses":0,"Zen_Project_Op_Writes":0,"Zen_Project_Chunk_Hits":0,"Zen_Project_Chunk_Misses":0,"Zen_Project_Chunk_Writes":0,"Zen_Project_Requests":0,"Zen_Project_BadRequests":0,"Zen_Project_Op_HitRatio":0.0,"Zen_Project_Chunk_HitRatio":0.0,"DDC_Summary_BackEnd":"InstalledDerivedDataBackendGraph","DDC_Summary_HasLocalCache":"true","DDC_Summary_HasSharedCache":"false","DDC_Summary_HasCloudCache":"false","DDC_Summary_HasZenCache":"true","DDC_Summary_TotalGetHits":1708.0,"DDC_Summary_TotalGetMisses":94.0,"DDC_Summary_TotalGets":1802.0,"DDC_Summary_TotalGetHitPct":0.947836,"DDC_Summary_GetMissPct":0.052164,"DDC_Summary_TotalPutHits":88.0,"DDC_Summary_TotalPutMisses":0.0,"DDC_Summary_TotalPuts":88.0,"DDC_Summary_TotalPutHitPct":1.0,"DDC_Summary_PutMissPct":0.0,"DDC_Summary_LocalGetHits":0.0,"DDC_Summary_LocalGetTotal":0.0,"DDC_Summary_LocalGetHitPct":0.0,"DDC_Summary_SharedGetHits":0.0,"DDC_Summary_SharedGetTotal":0.0,"DDC_Summary_SharedGetHitPct":0.0,"DDC_Summary_ZenLocalGetHits":600.0,"DDC_Summary_ZenLocalGetTotal":693.0,"DDC_Summary_ZenLocalGetHitPct":0.865801,"DDC_Summary_ZenRemoteGetHits":0.0,"DDC_Summary_ZenRemoteGetTotal":0.0,"DDC_Summary_ZenRemoteGetHitPct":0.0,"DDC_Summary_CloudGetHits":0.0,"DDC_Summary_CloudGetTotal":0.0,"DDC_Summary_CloudGetHitPct":0.0,"DDC_Summary_LocalLatency":0.0,"DDC_Summary_LocalReadSpeed":0.0,"DDC_Summary_LocalWriteSpeed":0.0,"DDC_Summary_SharedLatency":0.0,"DDC_Summary_SharedReadSpeed":0.0,"DDC_Summary_SharedWriteSpeed":0.0,"DDC_Summary_CloudLatency":0.0,"DDC_Summary_CloudReadSpeed":0.0,"DDC_Summary_CloudWriteSpeed":0.0}
{"EventName":"Core.DDC.Resource","TimestampUTC":1756823240.856000,"RecordId":36,"ProjectName":"WarehouseWreckage","ProjectID":"00000000000000000000000000000000","Session_ID":"{1CA7FCE3-412D-5A25-3428-5294C53E8240}","Session_Label":"","Session_StartUTC":1756823234.17,"Build_Configuration":"Development","Build_IsInternalBuild":false,"Build_IsPerforceBuild":false,"Build_IsPromotedBuild":true,"Build_BranchName":"++ue5+release-5.4","Build_Changelist":35576357,"Hardware_Platform":"Windows","Hardware_GPU":"","Hardware_CPU":"AMD Ryzen 5 9600X 6-Core Processor             ","Hardware_CPU_Cores_Physical":6,"Hardware_CPU_Cores_Logical":12,"Hardware_RAM":66182578176,"Hardware_ComputerName":"MVAT4","Config_IsEditor":true,"Config_IsUnattended":false,"Config_IsBuildMachine":false,"Config_IsRunningCommandlet":false,"Config_IsDebuggerPresent":false,"MapName":"OpenWorld","SchemaVersion":3,"LoadingName":"TotalEditorStartup","AssetType":"Texture (Inline)","Load_Count":124,"Load_TimeSec":0.011366,"Load_SizeMB":84.999616,"Build_Count":0,"Build_TimeSec":0.0,"Build_SizeMB":0.0,"Total_Count":124,"Total_TimeSec":0.011366,"Total_SizeMB":84,"Efficiency":1.0,"Thread_TimeSec":0.011366}
{"EventName":"Core.DDC.Resource","TimestampUTC":1756823240.857000,"RecordId":37,"ProjectName":"WarehouseWreckage","ProjectID":"00000000000000000000000000000000","Session_ID":"{1CA7FCE3-412D-5A25-3428-5294C53E8240}","Session_Label":"","Session_StartUTC":1756823234.17,"Build_Configuration":"Development","Build_IsInternalBuild":false,"Build_IsPerforceBuild":false,"Build_IsPromotedBuild":true,"Build_BranchName":"++ue5+release-5.4","Build_Changelist":35576357,"Hardware_Platform":"Windows","Hardware_GPU":"","Hardware_CPU":"AMD Ryzen 5 9600X 6-Core Processor             ","Hardware_CPU_Cores_Physical":6,"Hardware_CPU_Cores_Logical":12,"Hardware_RAM":66182578176,"Hardware_ComputerName":"MVAT4","Config_IsEditor":true,"Config_IsUnattended":false,"Config_IsBuildMachine":false,"Config_IsRunningCommandlet":false,"Config_IsDebuggerPresent":false,"MapName":"OpenWorld","SchemaVersion":3,"LoadingName":"TotalEditorStartup","AssetType":"Texture (Streaming)","Load_Count":32,"Load_TimeSec":0.003793,"Load_SizeMB":9.146484,"Build_Count":0,"Build_TimeSec":0.0,"Build_SizeMB":0.0,"Total_Count":32,"Total_TimeSec":0.003793,"Total_SizeMB":9,"Efficiency":1.0,"Thread_TimeSec":0.003793}
{"EventName":"Core.DDC.Resource","TimestampUTC":1756823240.858000,"RecordId":38,"ProjectName":"WarehouseWreckage","ProjectID":"00000000000000000000000000000000","Session_ID":"{1CA7FCE3-412D-5A25-3428-5294C53E8240}","Session_Label":"","Session_StartUTC":1756823234.17,"Build_Configuration":"Development","Build_IsInternalBuild":false,"Build_IsPerforceBuild":false,"Build_IsPromotedBuild":true,"Build_BranchName":"++ue5+release-5.4","Build_Changelist":35576357,"Hardware_Platform":"Windows","Hardware_GPU":"","Hardware_CPU":"AMD Ryzen 5 9600X 6-Core Processor             ","Hardware_CPU_Cores_Physical":6,"Hardware_CPU_Cores_Logical":12,"Hardware_RAM":66182578176,"Hardware_ComputerName":"MVAT4","Config_IsEditor":true,"Config_IsUnattended":false,"Config_IsBuildMachine":false,"Config_IsRunningCommandlet":false,"Config_IsDebuggerPresent":false,"MapName":"OpenWorld","SchemaVersion":3,"LoadingName":"TotalEditorStartup","AssetType":"StaticMesh","Load_Count":38,"Load_TimeSec":0.008605,"Load_SizeMB":4.451952,"Build_Count":0,"Build_TimeSec":0.0,"Build_SizeMB":0.0,"Total_Count":38,"Total_TimeSec":0.008605,"Total_SizeMB":4,"Efficiency":1.0,"Thread_TimeSec":0.006869}
{"EventName":"Core.DDC.Resource","TimestampUTC":1756823240.859000,"RecordId":39,"ProjectName":"WarehouseWreckage","ProjectID":"00000000000000000000000000000000","Session_ID":"{1CA7FCE3-412D-5A25-3428-5294C53E8240}","Session_Label":"","Session_StartUTC":1756823234.17,"Build_Configuration":"Development","Build_IsInternalBuild":false,"Build_IsPerforceBuild":false,"Build_IsPromotedBuild":true,"Build_BranchName":"++ue5+release-5.4","Build_Changelist":35576357,"Hardware_Platform":"Windows","Hardware_GPU":"","Hardware_CPU":"AMD Ryzen 5 9600X 6-Core Processor             ","Hardware_CPU_Cores_Physical":6,"Hardware_CPU_Cores_Logical":12,"Hardware_RAM":66182578176,"Hardware_ComputerName":"MVAT4","Config_IsEditor":true,"Config_IsUnattended":false,"Config_IsBuildMachine":false,"Config_IsRunningCommandlet":false,"Config_IsDebuggerPresent":false,"MapName":"OpenWorld","SchemaVersion":3,"LoadingName":"TotalEditorStartup","AssetType":"GlobalShader","Load_Count":346,"Load_TimeSec":0.03925,"Load_SizeMB":106.153169,"Build_Count":0,"Build_TimeSec":0.0,"Build_SizeMB":0.0,"Total_Count":346,"Total_TimeSec":0.03925,"Total_SizeMB":106,"Efficiency":1.0,"Thread_TimeSec":0.03925}
{"EventName":"Core.DDC.Resource","TimestampUTC":1756823240.859000,"RecordId":40,"ProjectName":"WarehouseWreckage","ProjectID":"00000000000000000000000000000000","Session_ID":"{1CA7FCE3-412D-5A25-3428-5294C53E8240}","Session_Label":"","Session_StartUTC":1756823234.17,"Build_Configuration":"Development","Build_IsInternalBuild":false,"Build_IsPerforceBuild":false,"Build_IsPromotedBuild":true,"Build_BranchName":"++ue5+release-5.4","Build_Changelist":35576357,"Hardware_Platform":"Windows","Hardware_GPU":"","Hardware_CPU":"AMD Ryzen 5 9600X 6-Core Processor             ","Hardware_CPU_Cores_Physical":6,"Hardware_CPU_Cores_Logical":12,"Hardware_RAM":66182578176,"Hardware_ComputerName":"MVAT4","Config_IsEditor":true,"Config_IsUnattended":false,"Config_IsBuildMachine":false,"Config_IsRunningCommandlet":false,"Config_IsDebuggerPresent":false,"MapName":"OpenWorld","SchemaVersion":3,"LoadingName":"TotalEditorStartup","AssetType":"BodySetup","Load_Count":1,"Load_TimeSec":0.001331,"Load_SizeMB":1.456863,"Build_Count":0,"Build_TimeSec":0.0,"Build_SizeMB":0.0,"Total_Count":1,"Total_TimeSec":0.001331,"Total_SizeMB":1,"Efficiency":1.0,"Thread_TimeSec":0.001331}
{"EventName":"Core.DDC.Resource","TimestampUTC":1756823240.860000,"RecordId":41,"ProjectName":"WarehouseWreckage","ProjectID":"00000000000000000000000000000000","Session_ID":"{1CA7FCE3-412D-5A25-3428-5294C53E8240}","Session_Label":"","Session_StartUTC":1756823234.17,"Build_Configuration":"Development","Build_IsInternalBuild":false,"Build_IsPerforceBuild":false,"Build_IsPromotedBuild":true,"Build_BranchName":"++ue5+release-5.4","Build_Changelist":35576357,"Hardware_Platform":"Windows","Hardware_GPU":"","Hardware_CPU":"AMD Ryzen 5 9600X 6-Core Processor             ","Hardware_CPU_Cores_Physical":6,"Hardware_CPU_Cores_Logical":12,"Hardware_RAM":66182578176,"Hardware_ComputerName":"MVAT4","Config_IsEditor":true,"Config_IsUnattended":false,"Config_IsBuildMachine":false,"Config_IsRunningCommandlet":false,"Config_IsDebuggerPresent":false,"MapName":"OpenWorld","SchemaVersion":3,"LoadingName":"TotalEditorStartup","AssetType":"CardRepresentation","Load_Count":38,"Load_TimeSec":0.002367,"Load_SizeMB":0.01085,"Build_Count":0,"Build_TimeSec":0.0,"Build_SizeMB":0.0,"Total_Count":38,"Total_TimeSec":0.002367,"Total_SizeMB":0,"Efficiency":1.0,"Thread_TimeSec":0.001906}
{"EventName":"Core.DDC.Resource","TimestampUTC":1756823240.861000,"RecordId":42,"ProjectName":"WarehouseWreckage","ProjectID":"00000000000000000000000000000000","Session_ID":"{1CA7FCE3-412D-5A25-3428-5294C53E8240}","Session_Label":"","Session_StartUTC":1756823234.17,"Build_Configuration":"Development","Build_IsInternalBuild":false,"Build_IsPerforceBuild":false,"Build_IsPromotedBuild":true,"Build_BranchName":"++ue5+release-5.4","Build_Changelist":35576357,"Hardware_Platform":"Windows","Hardware_GPU":"","Hardware_CPU":"AMD Ryzen 5 9600X 6-Core Processor             ","Hardware_CPU_Cores_Physical":6,"Hardware_CPU_Cores_Logical":12,"Hardware_RAM":66182578176,"Hardware_ComputerName":"MVAT4","Config_IsEditor":true,"Config_IsUnattended":false,"Config_IsBuildMachine":false,"Config_IsRunningCommandlet":false,"Config_IsDebuggerPresent":false,"MapName":"OpenWorld","SchemaVersion":3,"LoadingName":"TotalEditorStartup","AssetType":"MaterialShader","Load_Count":4,"Load_TimeSec":0.00698,"Load_SizeMB":17.932115,"Build_Count":0,"Build_TimeSec":0.0,"Build_SizeMB":0.0,"Total_Count":4,"Total_TimeSec":0.00698,"Total_SizeMB":17,"Efficiency":1.0,"Thread_TimeSec":0.00698}
{"EventName":"Core.DDC.Resource","TimestampUTC":1756823240.862000,"RecordId":43,"ProjectName":"WarehouseWreckage","ProjectID":"00000000000000000000000000000000","Session_ID":"{1CA7FCE3-412D-5A25-3428-5294C53E8240}","Session_Label":"","Session_StartUTC":1756823234.17,"Build_Configuration":"Development","Build_IsInternalBuild":false,"Build_IsPerforceBuild":false,"Build_IsPromotedBuild":true,"Build_BranchName":"++ue5+release-5.4","Build_Changelist":35576357,"Hardware_Platform":"Windows","Hardware_GPU":"","Hardware_CPU":"AMD Ryzen 5 9600X 6-Core Processor             ","Hardware_CPU_Cores_Physical":6,"Hardware_CPU_Cores_Logical":12,"Hardware_RAM":66182578176,"Hardware_ComputerName":"MVAT4","Config_IsEditor":true,"Config_IsUnattended":false,"Config_IsBuildMachine":false,"Config_IsRunningCommandlet":false,"Config_IsDebuggerPresent":false,"MapName":"OpenWorld","SchemaVersion":3,"LoadingName":"TotalEditorStartup","AssetType":"DistanceField","Load_Count":38,"Load_TimeSec":0.00999,"Load_SizeMB":5.889612,"Build_Count":0,"Build_TimeSec":0.0,"Build_SizeMB":0.0,"Total_Count":38,"Total_TimeSec":0.00999,"Total_SizeMB":5,"Efficiency":1.0,"Thread_TimeSec":0.007136}
{"EventName":"Core.DDC.Resource","TimestampUTC":1756823240.862000,"RecordId":44,"ProjectName":"WarehouseWreckage","ProjectID":"00000000000000000000000000000000","Session_ID":"{1CA7FCE3-412D-5A25-3428-5294C53E8240}","Session_Label":"","Session_StartUTC":1756823234.17,"Build_Configuration":"Development","Build_IsInternalBuild":false,"Build_IsPerforceBuild":false,"Build_IsPromotedBuild":true,"Build_BranchName":"++ue5+release-5.4","Build_Changelist":35576357,"Hardware_Platform":"Windows","Hardware_GPU":"","Hardware_CPU":"AMD Ryzen 5 9600X 6-Core Processor             ","Hardware_CPU_Cores_Physical":6,"Hardware_CPU_Cores_Logical":12,"Hardware_RAM":66182578176,"Hardware_ComputerName":"MVAT4","Config_IsEditor":true,"Config_IsUnattended":false,"Config_IsBuildMachine":false,"Config_IsRunningCommandlet":false,"Config_IsDebuggerPresent":false,"MapName":"OpenWorld","SchemaVersion":3,"LoadingName":"TotalEditorStartup","AssetType":"Audio (Inline)","Load_Count":8,"Load_TimeSec":0.002669,"Load_SizeMB":0.006736,"Build_Count":0,"Build_TimeSec":0.0,"Build_SizeMB":0.0,"Total_Count":8,"Total_TimeSec":0.002669,"Total_SizeMB":0,"Efficiency":1.0,"Thread_TimeSec":0.002669}
{"EventName":"Core.DDC.Resource","TimestampUTC":1756823240.863000,"RecordId":45,"ProjectName":"WarehouseWreckage","ProjectID":"00000000000000000000000000000000","Session_ID":"{1CA7FCE3-412D-5A25-3428-5294C53E8240}","Session_Label":"","Session_StartUTC":1756823234.17,"Build_Configuration":"Development","Build_IsInternalBuild":false,"Build_IsPerforceBuild":false,"Build_IsPromotedBuild":true,"Build_BranchName":"++ue5+release-5.4","Build_Changelist":35576357,"Hardware_Platform":"Windows","Hardware_GPU":"","Hardware_CPU":"AMD Ryzen 5 9600X 6-Core Processor             ","Hardware_CPU_Cores_Physical":6,"Hardware_CPU_Cores_Logical":12,"Hardware_RAM":66182578176,"Hardware_ComputerName":"MVAT4","Config_IsEditor":true,"Config_IsUnattended":false,"Config_IsBuildMachine":false,"Config_IsRunningCommandlet":false,"Config_IsDebuggerPresent":false,"MapName":"OpenWorld","SchemaVersion":3,"LoadingName":"TotalEditorStartup","AssetType":"LandscapeCollision (Heightfield)","Load_Count":0,"Load_TimeSec":0.0,"Load_SizeMB":0.0,"Build_Count":512,"Build_TimeSec":0.198202,"Build_SizeMB":24.52832,"Total_Count":512,"Total_TimeSec":0.198202,"Total_SizeMB":24,"Efficiency":0.0,"Thread_TimeSec":0.198202}
{"EventName":"Core.DDC.Resource","TimestampUTC":1756823240.864000,"RecordId":46,"ProjectName":"WarehouseWreckage","ProjectID":"00000000000000000000000000000000","Session_ID":"{1CA7FCE3-412D-5A25-3428-5294C53E8240}","Session_Label":"","Session_StartUTC":1756823234.17,"Build_Configuration":"Development","Build_IsInternalBuild":false,"Build_IsPerforceBuild":false,"Build_IsPromotedBuild":true,"Build_BranchName":"++ue5+release-5.4","Build_Changelist":35576357,"Hardware_Platform":"Windows","Hardware_GPU":"","Hardware_CPU":"AMD Ryzen 5 9600X 6-Core Processor             ","Hardware_CPU_Cores_Physical":6,"Hardware_CPU_Cores_Logical":12,"Hardware_RAM":66182578176,"Hardware_ComputerName":"MVAT4","Config_IsEditor":true,"Config_IsUnattended":false,"Config_IsBuildMachine":false,"Config_IsRunningCommandlet":false,"Config_IsDebuggerPresent":false,"MapName":"OpenWorld","SchemaVersion":3,"LoadingName":"TotalEditorStartup","AssetType":"NavCollision","Load_Count":37,"Load_TimeSec":0.001489,"Load_SizeMB":0.046027,"Build_Count":0,"Build_TimeSec":0.0,"Build_SizeMB":0.0,"Total_Count":37,"Total_TimeSec":0.001489,"Total_SizeMB":0,"Efficiency":1.0,"Thread_TimeSec":0.001227}
{"EventName":"Core.DDC.Resource","TimestampUTC":1756823240.865000,"RecordId":47,"ProjectName":"WarehouseWreckage","ProjectID":"00000000000000000000000000000000","Session_ID":"{1CA7FCE3-412D-5A25-3428-5294C53E8240}","Session_Label":"","Session_StartUTC":1756823234.17,"Build_Configuration":"Development","Build_IsInternalBuild":false,"Build_IsPerforceBuild":false,"Build_IsPromotedBuild":true,"Build_BranchName":"++ue5+release-5.4","Build_Changelist":35576357,"Hardware_Platform":"Windows","Hardware_GPU":"","Hardware_CPU":"AMD Ryzen 5 9600X 6-Core Processor             ","Hardware_CPU_Cores_Physical":6,"Hardware_CPU_Cores_Logical":12,"Hardware_RAM":66182578176,"Hardware_ComputerName":"MVAT4","Config_IsEditor":true,"Config_IsUnattended":false,"Config_IsBuildMachine":false,"Config_IsRunningCommandlet":false,"Config_IsDebuggerPresent":false,"MapName":"OpenWorld","SchemaVersion":3,"LoadingName":"TotalEditorStartup","AssetType":"Total","Load_Count":666,"Load_TimeSec":0.08784,"Load_SizeMB":230.093424,"Build_Count":512,"Build_TimeSec":0.198202,"Build_SizeMB":24.52832,"Total_Count":1178,"Total_TimeSec":0.286042,"Total_SizeMB":254,"Efficiency":0.565365,"Thread_TimeSec":0.280729}
{"EventName":"Core.DDC.Summary","TimestampUTC":1756823240.866000,"RecordId":48,"ProjectName":"WarehouseWreckage","ProjectID":"00000000000000000000000000000000","Session_ID":"{1CA7FCE3-412D-5A25-3428-5294C53E8240}","Session_Label":"","Session_StartUTC":1756823234.17,"Build_Configuration":"Development","Build_IsInternalBuild":false,"Build_IsPerforceBuild":false,"Build_IsPromotedBuild":true,"Build_BranchName":"++ue5+release-5.4","Build_Changelist":35576357,"Hardware_Platform":"Windows","Hardware_GPU":"","Hardware_CPU":"AMD Ryzen 5 9600X 6-Core Processor             ","Hardware_CPU_Cores_Physical":6,"Hardware_CPU_Cores_Logical":12,"Hardware_RAM":66182578176,"Hardware_ComputerName":"MVAT4","Config_IsEditor":true,"Config_IsUnattended":false,"Config_IsBuildMachine":false,"Config_IsRunningCommandlet":false,"Config_IsDebuggerPresent":false,"MapName":"OpenWorld","SchemaVersion":3,"LoadingName":"TotalEditorStartup","BackEnd":"InstalledDerivedDataBackendGraph","HasLocalCache":"true","HasSharedCache":"false","HasCloudCache":"false","HasZenCache":"true","TotalGetHits":1708.0,"TotalGetMisses":94.0,"TotalGets":1802.0,"TotalGetHitPct":0.947836,"GetMissPct":0.052164,"TotalPutHits":88.0,"TotalPutMisses":0.0,"TotalPuts":88.0,"TotalPutHitPct":1.0,"PutMissPct":0.0,"LocalGetHits":0.0,"LocalGetTotal":0.0,"LocalGetHitPct":0.0,"SharedGetHits":0.0,"SharedGetTotal":0.0,"SharedGetHitPct":0.0,"ZenLocalGetHits":600.0,"ZenLocalGetTotal":693.0,"ZenLocalGetHitPct":0.865801,"ZenRemoteGetHits":0.0,"ZenRemoteGetTotal":0.0,"ZenRemoteGetHitPct":0.0,"CloudGetHits":0.0,"CloudGetTotal":0.0,"CloudGetHitPct":0.0,"LocalLatency":0.0,"LocalReadSpeed":0.0,"LocalWriteSpeed":0.0,"SharedLatency":0.0,"SharedReadSpeed":0.0,"SharedWriteSpeed":0.0,"CloudLatency":0.0,"CloudReadSpeed":0.0,"CloudWriteSpeed":0.0}
{"EventName":"Core.Zen","TimestampUTC":1756823240.867000,"RecordId":49,"ProjectName":"WarehouseWreckage","ProjectID":"00000000000000000000000000000000","Session_ID":"{1CA7FCE3-412D-5A25-3428-5294C53E8240}","Session_Label":"","Session_StartUTC":1756823234.17,"Build_Configuration":"Development","Build_IsInternalBuild":false,"Build_IsPerforceBuild":false,"Build_IsPromotedBuild":true,"Build_BranchName":"++ue5+release-5.4","Build_Changelist":35576357,"Hardware_Platform":"Windows","Hardware_GPU":"","Hardware_CPU":"AMD Ryzen 5 9600X 6-Core Processor             ","Hardware_CPU_Cores_Physical":6,"Hardware_CPU_Cores_Logical":12,"Hardware_RAM":66182578176,"Hardware_ComputerName":"MVAT4","Config_IsEditor":true,"Config_IsUnattended":false,"Config_IsBuildMachine":false,"Config_IsRunningCommandlet":false,"Config_IsDebuggerPresent":false,"MapName":"OpenWorld","SchemaVersion":1,"LoadingName":"TotalEditorStartup","Zen_Enabled":true,"Zen_Cache_Size_Disk":164202191.0,"Zen_Cache_Size_Memory":132856.0,"Zen_Cache_Hits":1190,"Zen_Cache_Misses":6,"Zen_Cache_Writes":173,"Zen_Cache_HitRatio":0.994983,"Zen_Cache_Cas_Hits":1070,"Zen_Cache_Cas_Misses":0,"Zen_Cache_Cas_Writes":0,"Zen_Cache_Requests":1051,"Zen_Cache_BadRequests":0,"Zen_Cache_Requests_Count":1051,"Zen_Cache_Requests_RateMean":6.806388,"Zen_Cache_Requests_TAverage":0.000057,"Zen_Cache_Requests_TMin":0.000006,"Zen_Cache_Requests_TMax":0.001146,"Zen_Cache_TotalUploadedMB":0.0,"Zen_Upstream_TotalDownloadedMB":0.0,"Zen_Upstream_TotalUploadedMB":0.0,"Zen_Upstream_Requests_Count":0,"Zen_Upstream_Requests_RateMean":0.0,"Zen_Upstream_Requests_TAverage":0.0,"Zen_Upstream_Requests_TMin":0.0,"Zen_Upstream_Requests_TMax":0.0,"Zen_Cas_Size_Large":0,"Zen_Cas_Size_Small":14398188,"Zen_Cas_Size_Tiny":112102,"Zen_Cas_Size_Total":14510290,"Zen_Project_Size_Disk":0.0,"Zen_Project_Size_Memory":0.0,"Zen_Project_WriteCount":0,"Zen_Project_ReadCount":0,"Zen_Project_DeleteCount":0,"Zen_Project_Oplog_WriteCount":0,"Zen_Project_Oplog_ReadCount":0,"Zen_Project_Oplog_DeleteCount":0,"Zen_Project_Op_Hits":0,"Zen_Project_Op_Misses":0,"Zen_Project_Op_Writes":0,"Zen_Project_Chunk_Hits":0,"Zen_Project_Chunk_Misses":0,"Zen_Project_Chunk_Writes":0,"Zen_Project_Requests":0,"Zen_Project_BadRequests":0,"Zen_Project_Op_HitRatio":0.0,"Zen_Project_Chunk_HitRatio":0.0}
{"EventName":"Span","TimestampUTC":1756823242.030000,"RecordId":50,"ProjectName":"WarehouseWreckage","ProjectID":"00000000000000000000000000000000","Session_ID":"{1CA7FCE3-412D-5A25-3428-5294C53E8240}","Session_Label":"","Session_StartUTC":1756823234.17,"Build_Configuration":"Development","Build_IsInternalBuild":false,"Build_IsPerforceBuild":false,"Build_IsPromotedBuild":true,"Build_BranchName":"++ue5+release-5.4","Build_Changelist":35576357,"Hardware_Platform":"Windows","Hardware_GPU":"","Hardware_CPU":"AMD Ryzen 5 9600X 6-Core Processor             ","Hardware_CPU_Cores_Physical":6,"Hardware_CPU_Cores_Logical":12,"Hardware_RAM":66182578176,"Hardware_ComputerName":"MVAT4","Config_IsEditor":true,"Config_IsUnattended":false,"Config_IsBuildMachine":false,"Config_IsRunningCommandlet":false,"Config_IsDebuggerPresent":false,"MapName":"OpenWorld","TaskName":"Validating Assets","SchemaVersion":1,"Span_Name":"ST Validating Assets","Span_GUID":"3295A8B84F6BCA81C6099CAB49992DEE","Span_ParentName":"Editor.Interact","Span_ThreadId":30336,"Span_Depth":3,"Span_StartUTC":1756823241.965,"Span_EndUTC":1756823242.03,"Span_TimeInSec":0.065}
{"EventName":"Editor.AssetRegistry.InitialScan","TimestampUTC":1756823242.033000,"RecordId":51,"ProjectName":"WarehouseWreckage","ProjectID":"00000000000000000000000000000000","Session_ID":"{1CA7FCE3-412D-5A25-3428-5294C53E8240}","Session_Label":"","Session_StartUTC":1756823234.17,"Build_Configuration":"Development","Build_IsInternalBuild":false,"Build_IsPerforceBuild":false,"Build_IsPromotedBuild":true,"Build_BranchName":"++ue5+release-5.4","Build_Changelist":35576357,"Hardware_Platform":"Windows","Hardware_GPU":"","Hardware_CPU":"AMD Ryzen 5 9600X 6-Core Processor             ","Hardware_CPU_Cores_Physical":6,"Hardware_CPU_Cores_Logical":12,"Hardware_RAM":66182578176,"Hardware_ComputerName":"MVAT4","Config_IsEditor":true,"Config_IsUnattended":false,"Config_IsBuildMachine":false,"Config_IsRunningCommandlet":false,"Config_IsDebuggerPresent":false,"SchemaVersion":1,"TotalDurationSeconds":5.520501,"TotalWorkSeconds":0.326372,"DiscoverySeconds":0.023749,"GatherSeconds":0.273189,"StoreSeconds":0.029434,"NumCachedDirectories":0,"NumUncachedDirectories":1350,"NumCachedAssetFiles":0,"NumUncachedAssetFiles":7447}
{"EventName":"Editor.AssetView.BackendFilter","TimestampUTC":1756823242.097000,"RecordId":52,"ProjectName":"WarehouseWreckage","ProjectID":"00000000000000000000000000000000","Session_ID":"{1CA7FCE3-412D-5A25-3428-5294C53E8240}","Session_Label":"","Session_StartUTC":1756823234.17,"Build_Configuration":"Development","Build_IsInternalBuild":false,"Build_IsPerforceBuild":false,"Build_IsPromotedBuild":true,"Build_BranchName":"++ue5+release-5.4","Build_Changelist":35576357,"Hardware_Platform":"Windows","Hardware_GPU":"","Hardware_CPU":"AMD Ryzen 5 9600X 6-Core Processor             ","Hardware_CPU_Cores_Physical":6,"Hardware_CPU_Cores_Logical":12,"Hardware_RAM":66182578176,"Hardware_ComputerName":"MVAT4","Config_IsEditor":true,"Config_IsUnattended":false,"Config_IsBuildMachine":false,"Config_IsRunningCommandlet":false,"Config_IsDebuggerPresent":false,"SchemaVersion":1,"ViewCorrelationGuid":"A1BA162C4CBDC8FF2741188DC7F0D761","FilterSessionCorrelationGuid":"F2CB705B41A92FE01D3E3DA60D50C04E","HasCustomItemSources":false,"RefreshSourceItemsDurationSeconds":0.002972,"NumBackendItems":11,"DataFilter":{"RecursivePaths":false,"ItemTypeFilter":"IncludeFolders | IncludeFiles","ItemCategoryFilter":"IncludeAssets | IncludeClasses | IncludeCollections | IncludeMisc","ItemAttributeFilter":"IncludeProject"}}
{"EventName":"Editor.AssetView.FrontendFilter","TimestampUTC":1756823242.097000,"RecordId":53,"ProjectName":"WarehouseWreckage","ProjectID":"00000000000000000000000000000000","Session_ID":"{1CA7FCE3-412D-5A25-3428-5294C53E8240}","Session_Label":"","Session_StartUTC":1756823234.17,"Build_Configuration":"Development","Build_IsInternalBuild":false,"Build_IsPerforceBuild":false,"Build_IsPromotedBuild":true,"Build_BranchName":"++ue5+release-5.4","Build_Changelist":35576357,"Hardware_Platform":"Windows","Hardware_GPU":"","Hardware_CPU":"AMD Ryzen 5 9600X 6-Core Processor             ","Hardware_CPU_Cores_Physical":6,"Hardware_CPU_Cores_Logical":12,"Hardware_RAM":66182578176,"Hardware_ComputerName":"MVAT4","Config_IsEditor":true,"Config_IsUnattended":false,"Config_IsBuildMachine":false,"Config_IsRunningCommandlet":false,"Config_IsDebuggerPresent":false,"SchemaVersion":1,"ViewCorrelationGuid":"A1BA162C4CBDC8FF2741188DC7F0D761","FilterSessionCorrelationGuid":"F2CB705B41A92FE01D3E3DA60D50C04E","TotalItemsToFilter":11,"PriorityItemsToFilter":0,"TotalResults":11,"AmortizeDurationSeconds":0.000042,"WorkDurationSeconds":0.000043,"ResultLatency":"0.000035","TimeUntilInteractionSeconds":"null","Completed":true,"FrontendFilters":["ShowOtherDevelopers","ShowRedirectors"]}
{"EventName":"Editor.AssetView.BackendFilter","TimestampUTC":1756823242.594000,"RecordId":54,"ProjectName":"WarehouseWreckage","ProjectID":"00000000000000000000000000000000","Session_ID":"{1CA7FCE3-412D-5A25-3428-5294C53E8240}","Session_Label":"","Session_StartUTC":1756823234.17,"Build_Configuration":"Development","Build_IsInternalBuild":false,"Build_IsPerforceBuild":false,"Build_IsPromotedBuild":true,"Build_BranchName":"++ue5+release-5.4","Build_Changelist":35576357,"Hardware_Platform":"Windows","Hardware_GPU":"","Hardware_CPU":"AMD Ryzen 5 9600X 6-Core Processor             ","Hardware_CPU_Cores_Physical":6,"Hardware_CPU_Cores_Logical":12,"Hardware_RAM":66182578176,"Hardware_ComputerName":"MVAT4","Config_IsEditor":true,"Config_IsUnattended":false,"Config_IsBuildMachine":false,"Config_IsRunningCommandlet":false,"Config_IsDebuggerPresent":false,"SchemaVersion":1,"ViewCorrelationGuid":"A1BA162C4CBDC8FF2741188DC7F0D761","FilterSessionCorrelationGuid":"C72C3EDB4C47681F2806D88370D1DDB1","HasCustomItemSources":false,"RefreshSourceItemsDurationSeconds":0.004512,"NumBackendItems":11,"DataFilter":{"RecursivePaths":false,"ItemTypeFilter":"IncludeFolders | IncludeFiles","ItemCategoryFilter":"IncludeAssets | IncludeClasses | IncludeCollections | IncludeMisc","ItemAttributeFilter":"IncludeProject"}}
{"EventName":"Editor.AssetView.FrontendFilter","TimestampUTC":1756823242.595000,"RecordId":55,"ProjectName":"WarehouseWreckage","ProjectID":"00000000000000000000000000000000","Session_ID":"{1CA7FCE3-412D-5A25-3428-5294C53E8240}","Session_Label":"","Session_StartUTC":1756823234.17,"Build_Configuration":"Development","Build_IsInternalBuild":false,"Build_IsPerforceBuild":false,"Build_IsPromotedBuild":true,"Build_BranchName":"++ue5+release-5.4","Build_Changelist":35576357,"Hardware_Platform":"Windows","Hardware_GPU":"","Hardware_CPU":"AMD Ryzen 5 9600X 6-Core Processor             ","Hardware_CPU_Cores_Physical":6,"Hardware_CPU_Cores_Logical":12,"Hardware_RAM":66182578176,"Hardware_ComputerName":"MVAT4","Config_IsEditor":true,"Config_IsUnattended":false,"Config_IsBuildMachine":false,"Config_IsRunningCommandlet":false,"Config_IsDebuggerPresent":false,"SchemaVersion":1,"ViewCorrelationGuid":"A1BA162C4CBDC8FF2741188DC7F0D761","FilterSessionCorrelationGuid":"C72C3EDB4C47681F2806D88370D1DDB1","TotalItemsToFilter":11,"PriorityItemsToFilter":0,"TotalResults":11,"AmortizeDurationSeconds":0.000035,"WorkDurationSeconds":0.000036,"ResultLatency":"0.000027","TimeUntilInteractionSeconds":"null","Completed":true,"FrontendFilters":["ShowOtherDevelopers","ShowRedirectors"]}
{"EventName":"Span","TimestampUTC":1756823244.212000,"RecordId":56,"ProjectName":"WarehouseWreckage","ProjectID":"00000000000000000000000000000000","Session_ID":"{1CA7FCE3-412D-5A25-3428-5294C53E8240}","Session_Label":"","Session_StartUTC":1756823234.17,"Build_Configuration":"Development","Build_IsInternalBuild":false,"Build_IsPerforceBuild":false,"Build_IsPromotedBuild":true,"Build_BranchName":"++ue5+release-5.4","Build_Changelist":35576357,"Hardware_Platform":"Windows","Hardware_GPU":"","Hardware_CPU":"AMD Ryzen 5 9600X 6-Core Processor             ","Hardware_CPU_Cores_Physical":6,"Hardware_CPU_Cores_Logical":12,"Hardware_RAM":66182578176,"Hardware_ComputerName":"MVAT4","Config_IsEditor":true,"Config_IsUnattended":false,"Config_IsBuildMachine":false,"Config_IsRunningCommandlet":false,"Config_IsDebuggerPresent":false,"SchemaVersion":1,"Span_Name":"Session","Span_GUID":"D1440F67424BF58EE1310485CAE5C51B","Span_ParentName":"","Span_ThreadId":30336,"Span_Depth":0,"Span_StartUTC":1756823234.173,"Span_EndUTC":1756823244.212,"Span_TimeInSec":10.039}
{"EventName":"Span","TimestampUTC":1756823244.214000,"RecordId":57,"ProjectName":"WarehouseWreckage","ProjectID":"00000000000000000000000000000000","Session_ID":"{1CA7FCE3-412D-5A25-3428-5294C53E8240}","Session_Label":"","Session_StartUTC":1756823234.17,"Build_Configuration":"Development","Build_IsInternalBuild":false,"Build_IsPerforceBuild":false,"Build_IsPromotedBuild":true,"Build_BranchName":"++ue5+release-5.4","Build_Changelist":35576357,"Hardware_Platform":"Windows","Hardware_GPU":"","Hardware_CPU":"AMD Ryzen 5 9600X 6-Core Processor             ","Hardware_CPU_Cores_Physical":6,"Hardware_CPU_Cores_Logical":12,"Hardware_RAM":66182578176,"Hardware_ComputerName":"MVAT4","Config_IsEditor":true,"Config_IsUnattended":false,"Config_IsBuildMachine":false,"Config_IsRunningCommandlet":false,"Config_IsDebuggerPresent":false,"MapName":"OpenWorld","SchemaVersion":1,"Span_Name":"Editor","Span_GUID":"54FB41B647C01EAFC7F3618C90830A1D","Span_ParentName":"Session","Span_ThreadId":30336,"Span_Depth":1,"Span_StartUTC":1756823234.173,"Span_EndUTC":1756823244.214,"Span_TimeInSec":10.041}
{"EventName":"Span","TimestampUTC":1756823244.214000,"RecordId":58,"ProjectName":"WarehouseWreckage","ProjectID":"00000000000000000000000000000000","Session_ID":"{1CA7FCE3-412D-5A25-3428-5294C53E8240}","Session_Label":"","Session_StartUTC":1756823234.17,"Build_Configuration":"Development","Build_IsInternalBuild":false,"Build_IsPerforceBuild":false,"Build_IsPromotedBuild":true,"Build_BranchName":"++ue5+release-5.4","Build_Changelist":35576357,"Hardware_Platform":"Windows","Hardware_GPU":"","Hardware_CPU":"AMD Ryzen 5 9600X 6-Core Processor             ","Hardware_CPU_Cores_Physical":6,"Hardware_CPU_Cores_Logical":12,"Hardware_RAM":66182578176,"Hardware_ComputerName":"MVAT4","Config_IsEditor":true,"Config_IsUnattended":false,"Config_IsBuildMachine":false,"Config_IsRunningCommandlet":false,"Config_IsDebuggerPresent":false,"MapName":"OpenWorld","SchemaVersion":1,"Span_Name":"Editor.Interact","Span_GUID":"FE90DE004BE9D23DE7B40AA4F374DED7","Span_ParentName":"Editor","Span_ThreadId":30336,"Span_Depth":2,"Span_StartUTC":1756823240.855,"Span_EndUTC":1756823244.214,"Span_TimeInSec":3.359}
{"EventName":"Span","TimestampUTC":1756823244.215000,"RecordId":59,"ProjectName":"WarehouseWreckage","ProjectID":"00000000000000000000000000000000","Session_ID":"{1CA7FCE3-412D-5A25-3428-5294C53E8240}","Session_Label":"","Session_StartUTC":1756823234.17,"Build_Configuration":"Development","Build_IsInternalBuild":false,"Build_IsPerforceBuild":false,"Build_IsPromotedBuild":true,"Build_BranchName":"++ue5+release-5.4","Build_Changelist":35576357,"Hardware_Platform":"Windows","Hardware_GPU":"","Hardware_CPU":"AMD Ryzen 5 9600X 6-Core Processor             ","Hardware_CPU_Cores_Physical":6,"Hardware_CPU_Cores_Logical":12,"Hardware_RAM":66182578176,"Hardware_ComputerName":"MVAT4","Config_IsEditor":true,"Config_IsUnattended":false,"Config_IsBuildMachine":false,"Config_IsRunningCommandlet":false,"Config_IsDebuggerPresent":false,"MapName":"OpenWorld","SchemaVersion":1,"Span_Name":"Hitching","Span_GUID":"86A10BBB46CE9E82FA7757BD2B697DE3","Span_ParentName":"Editor.Interact","Span_ThreadId":30336,"Span_Depth":3,"Span_StartUTC":1756823242.574,"Span_EndUTC":1756823244.215,"Span_TimeInSec":1.641}
{"EventName":"Span","TimestampUTC":1756823244.216000,"RecordId":60,"ProjectName":"WarehouseWreckage","ProjectID":"00000000000000000000000000000000","Session_ID":"{1CA7FCE3-412D-5A25-3428-5294C53E8240}","Session_Label":"","Session_StartUTC":1756823234.17,"Build_Configuration":"Development","Build_IsInternalBuild":false,"Build_IsPerforceBuild":false,"Build_IsPromotedBuild":true,"Build_BranchName":"++ue5+release-5.4","Build_Changelist":35576357,"Hardware_Platform":"Windows","Hardware_GPU":"","Hardware_CPU":"AMD Ryzen 5 9600X 6-Core Processor             ","Hardware_CPU_Cores_Physical":6,"Hardware_CPU_Cores_Logical":12,"Hardware_RAM":66182578176,"Hardware_ComputerName":"MVAT4","Config_IsEditor":true,"Config_IsUnattended":false,"Config_IsBuildMachine":false,"Config_IsRunningCommandlet":false,"Config_IsDebuggerPresent":false,"MapName":"OpenWorld","SchemaVersion":1,"Span_Name":"Asset Registry Scan","Span_GUID":"4DFE95F84054AF8CA73A17A774884232","Span_ParentName":"Hitching","Span_ThreadId":30336,"Span_Depth":4,"Span_StartUTC":1756823242.574,"Span_EndUTC":1756823244.216,"Span_TimeInSec":1.642}
{"EventName":"EndSession","TimestampUTC":1756823244.217000,"RecordId":61,"ProjectName":"WarehouseWreckage","ProjectID":"00000000000000000000000000000000","Session_ID":"{1CA7FCE3-412D-5A25-3428-5294C53E8240}","Session_Label":"","Session_StartUTC":1756823234.17,"Build_Configuration":"Development","Build_IsInternalBuild":false,"Build_IsPerforceBuild":false,"Build_IsPromotedBuild":true,"Build_BranchName":"++ue5+release-5.4","Build_Changelist":35576357,"Hardware_Platform":"Windows","Hardware_GPU":"","Hardware_CPU":"AMD Ryzen 5 9600X 6-Core Processor             ","Hardware_CPU_Cores_Physical":6,"Hardware_CPU_Cores_Logical":12,"Hardware_RAM":66182578176,"Hardware_ComputerName":"MVAT4","Config_IsEditor":true,"Config_IsUnattended":false,"Config_IsBuildMachine":false,"Config_IsRunningCommandlet":false,"Config_IsDebuggerPresent":false}
